Workbook

Sheet 0. Review & Changelog
A1: ZEZAMII CLOUD — MODEL REVIEW & CHANGELOG (v53 → v54)
A2: Independent review + reconciliation to FY26 P&L actuals. Open in Excel/Google Sheets — workbook is set to full-recalc on load.
A4: FIX #1 — Base case = Standalone (LSC not committed)
B5: Dashboard!B5 | C5: Growth scenario set M → S. S = standalone (no LSC). M/L are upside contingent on LSC signing.
B6: Valuation!C41:E43 | C6: LSC strategic-premium attribution set to 0. Base pre-money is now FINANCIAL-ONLY. Restore HW 0.5 / accel 1.0 / panel 1.0 when LSC commits.
A8: FIX #2 — One engine (display reconciled to revenue)
B9: Dashboard!B11:F12 | C9: Site display was the Revenue-tab path (29→701); the P&L SaaS revenue is built from the Product Forecast blocks (active 920/1622/3236). Repointed the displayed sites to the Product Forecast active-site path so "sites → ARR" is consistent. No revenue number changed.
B10: OPEN DECISION | C10: ACaaS units still key off the Revenue-tab site path, and the S/standalone block is seeded at 62 Y1 sites vs ~30 FY26 actual direct capacity. To FULLY unify: either (a) re-seed Product Forecast S units to ~30 direct installs/yr (honest standalone), or (b) drive all module units from one site count via explicit attach rates. Tell me the standalone Y1 capacity and I will finish it.
A12: FIX #3 — Reconciled to FY26 actuals; single-value inputs; label fixes
B13: Assumptions!B41 | C13: Y0 ARR $120,000 → $139,000 (FY26 actual own-software recurring; excludes $202k Verkada resale).
B14: P&L / Revenue labels | C14: Hardware-margin labels corrected to the engine's real 25% Zezamii / 75% LSC (text said 20/35/65/15% in places; the math was always 25/75).
B15: Overview headline | C15: Stale Y5 sites 2,300/4,600 → 1,622/3,236; churn note 10% → 5% (engine value); Y0 ARR → $139k; refresh note.
B16: Note on churn/booking | C16: Earlier "churn 10%" and "booking 0%" were STALE CACHED values, not errors — the live inputs are churn 5% and booking 2.5%. Left unchanged.
A18: FY26 P&L reconciliation (anchor)
B19: Total income | C19: $1,179,811 — 29% licence / 71% one-off (hardware+install+consulting). Net loss $(319,583).
B20: Own-software recurring | C20: ~$139,428 (Cloud 24.5k + Rooms 46.4k + Lockers 50.3k + Vortex 16.9k + Zezamii 1.4k).
B21: Rooms ARR/site | C21: $1,545 (46,354 ÷ 30 customers) — the one hard bottom-up anchor.
B22: Hardware GM (FY26) | C22: −6.5% (Income $366.5k vs Cost $390.4k). Model assumes +25% — aspirational; flag.
A24: Limitations of this pass
B25: Recalc | C25: LibreOffice could not run headless in the build environment, so cached preview numbers are stale until you open the file (fullCalcOnLoad is set — Excel/Sheets recalc automatically). Only input/label cells were edited; no formula structure was changed.

Sheet 1. Overview
B1: ZEZAMII CLOUD - FINANCIAL MODEL
B2: Five-year forecast for LSC investment scenarios. Product-driven revenue across 6 SaaS lines + hardware, 3 growth scenarios.
B4: HOW TO USE THIS MODEL
B5: STEP 1 | C5: Review Assumptions
C6: Open the Assumptions sheet. Yellow cells are editable inputs: Cloud subscription tier prices, module prices, partner margin (35%), Y0 ARR ($120K existing), growth scenario inputs (Y1 sites + multiplier per S/M/L), churn rate (7%), team opex inputs, cost scaling targets.
B8: STEP 2 | C8: Select scenario on Dashboard
C9: On the Dashboard sheet, choose: - Growth scenario (B5): S / M / L (drives revenue) - Team model (B7): Product / Zezamii / Zezamii LSC (drives team costs/burn) - LSC Investment Scenario (B8): A / B / C / D (cash vs LSC equity mix)
B11: STEP 3 | C11: Edit product unit forecasts
C12: Open Product Forecast (sheet 4). Each scenario block (S, M, L) has yellow cells for unit counts per product per year. Type any number to override - revenue updates instantly. Defaults are seeded but fully editable.
B14: STEP 4 | C14: Review P&L
C15: P&L sheet shows the 5-year income statement for selected scenario. SaaS Revenue + Hardware Revenue, gross profit, margins. Updates automatically based on Dashboard selections and Product Forecast inputs.
B17: STEP 5 | C17: Check Cash Flow
C18: Cash Flow sheet shows opening cash, investment received (from LSC scenario), revenue collected, opex burned, closing cash position. Verify runway under selected scenarios.
B20: STEP 6 | C20: Review LSC investment decisions
C21: LSC Investment: enter pre-money valuation, see ownership % and runway by scenario A/B/C/D. LSC Returns: IRR/MOIC for LSC at each scenario. LSC Sensitivity: pre-money grids by EBITDA x multiple.
B23: STEP 7 | C23: Look at Valuation
C24: Valuation sheet shows pre-money derivation: ACaaS comps (Brivo, Openpath, Verkada), DCF on forecast, strategic premium (LSC partnership capture), build cost floor. Outputs Conservative / Base / Aggressive pre-money ranges.
B27: BUSINESS OVERVIEW
B28: - Zezamii Cloud is a B2B SaaS access control platform with integrated hardware sales.
B29: - Revenue streams: SaaS subscriptions (Cloud Base + Access + Rooms + Lockers + Integrate + ACaaS) + Hardware (locks + panels).
B30: - Target markets: commercial buildings, holiday parks, co-working, multi-tenant residential.
B31: - LSC partnership creates warm lead pipeline + lock pull-through (LSC sells hardware via Zezamii channel).
B33: GROWTH SCENARIO DEFINITIONS
B34: Scenario | C34: Description | D34: Y5 Cloud Sites | E34: Y5 SaaS ARR
B35: S | C35: Conservative / STANDALONE — no LSC channel. BASE CASE until LSC commits. | D35: 920 | E35: standalone — see Dashboard for live ARR
B36: M | C36: Plan-of-record - modest LSC channel commitment. M = S x 2.5. | D36: 1622 | E36: with LSC (upside)
B37: L | C37: Aggressive - full LSC channel commitment. L = S x 5. | D37: 3236 | E37: with LSC (upside)
B39: TEAM MODELS
B40: Model | C40: Y1 Opex | D40: Composition
B41: Product | C41: $608K/yr | D41: Lean: Glenn + Kishan + Duvan
B42: Zezamii | C42: $800K/yr | D42: Current team: Glenn + Kishan + Duvan + Warren + Luke
B43: Zezamii LSC | C43: $1.2M/yr | D43: Expanded: current team + trigger-based sales/support hires
B45: SHEET INDEX
B46: # | C46: Sheet | D46: Purpose
B47: 1 | C47: 1. Overview | D47: This page - narrative + instructions
B48: 2 | C48: 2. Dashboard | D48: Scenario selectors (growth / team / LSC investment)
B49: 3 | C49: 3. Assumptions | D49: All editable inputs (prices, churn, growth, costs)
B50: 4 | C50: 4. Product Forecast | D50: Unit counts + revenue per product per scenario (edit yellow cells)
B51: 5 | C51: 5. P&L | D51: 5-year income statement - SaaS + Hardware
B52: 6 | C52: 6. Cash Flow | D52: 5-year cash position + investment + runway
B53: 7 | C53: 7. Valuation | D53: Pre-money: comps + DCF + strategic premium + build cost
B54: 8 | C54: 8. LSC Investment | D54: Cash/equity investment scenarios A/B/C/D
B55: 9 | C55: 9. LSC Returns | D55: LSC IRR / MOIC at different pre-money points
B56: 10 | C56: 10. LSC Sensitivity | D56: Pre-money sensitivity grids
B57: 11 | C57: Revenue | D57: Site growth ramp, ARR build, hardware revenue (support)
... B61: 15 | C61: Team - LSC | D61: Team cost detail (support)
B63: KEY EDITABLE ASSUMPTIONS (live cell references)
B64: What | C64: Cell | D64: Current
B65: Cloud Small price (/yr) | C65: Assumptions!B5 | D65: ='3. Assumptions'!B5
B66: Cloud Medium price (/yr) | C66: Assumptions!B6 | D66: ='3. Assumptions'!B6
B67: Cloud Large price (/yr) | C67: Assumptions!B7 | D67: ='3. Assumptions'!B7
B68: Cloud Enterprise price (/yr) | C68: Assumptions!B8 | D68: ='3. Assumptions'!B8
B69: Partner Margin % | C69: Assumptions!B21 | D69: ='3. Assumptions'!B21
B70: S - Y1 sites | C70: Assumptions!B28 | D70: ='3. Assumptions'!B28
B71: S - multiplier | C71: Assumptions!B31 | D71: ='3. Assumptions'!B31
B72: M - Y1 sites | C72: Assumptions!B29 | D72: ='3. Assumptions'!B29
B73: M - multiplier | C73: Assumptions!B32 | D73: ='3. Assumptions'!B32
B74: L - Y1 sites | C74: Assumptions!B30 | D74: ='3. Assumptions'!B30
B75: L - multiplier | C75: Assumptions!B33 | D75: ='3. Assumptions'!B33
B76: Annual churn rate | C76: Assumptions!B35 | D76: 0.05
B77: Y0 existing sites | C77: Assumptions!B40 | D77: ='3. Assumptions'!B40
B78: Y0 ARR | C78: Assumptions!B41 | D78: 139000
B80: v54 — reconciled to FY26 actuals ($139k Y0); base=S standalone; LSC premium stripped until commitment; Dashboard site display repointed to Product Forecast (revenue engine).

Sheet 2. Dashboard
A1: ZEZAMII CLOUD
A2: Executive Summary — 5-Year Model
A4: MODEL SETTINGS
A5: Growth Scenario | B5: S | C5: S = STANDALONE (base until LSC commits) | M/L add modest/full LSC (upside) | D5: M = Base | E5: L = Aggressive
A6: ACaaS Enabled | B6: Yes | C6: Yes = ACaaS path (panels + recurring). No = Alt path (digital locks + access integrations @ 65% of ACaaS revenue; panels zero).
A7: Team Model | B7: Product
A8: LSC Investment Scenario | B8: A | C8: A=All Cash | B=Blended | C=Equity Heavy | D=Custom
A9: 5-YEAR FINANCIAL SUMMARY
A10: Metric | B10: Year 1 | C10: Year 2 | D10: Year 3 | E10: Year 4 | F10: Year 5 | G10: Total
A11: New Sites | B11: =IF($B$5="S",'4. Product Forecast'!C8,IF($B$5="M",'4. Product Forecast'!C40,'4. Product Forecast'!C72)) | C11: =IF($B$5="S",'4. Product Forecast'!D8,IF($B$5="M",'4. Product Forecast'!D40,'4. Product Forecast'!D72)) | D11: =IF($B$5="S",'4. Product Forecast'!E8,IF($B$5="M",'4. Product Forecast'!E40,'4. Product Forecast'!E72)) | E11: =IF($B$5="S",'4. Product Forecast'!F8,IF($B$5="M",'4. Product Forecast'!F40,'4. Product Forecast'!F72)) | F11: =IF($B$5="S",'4. Product Forecast'!G8,IF($B$5="M",'4. Product Forecast'!G40,'4. Product Forecast'!G72)) | G11: =SUM(B11:F11) | H11: Repointed to Product Forecast active-site path (the engine that generates SaaS revenue)
A12: Cumulative Sites | B12: =IF($B$5="S",'4. Product Forecast'!C7,IF($B$5="M",'4. Product Forecast'!C39,'4. Product Forecast'!C71)) | C12: =IF($B$5="S",'4. Product Forecast'!D7,IF($B$5="M",'4. Product Forecast'!D39,'4. Product Forecast'!D71)) | D12: =IF($B$5="S",'4. Product Forecast'!E7,IF($B$5="M",'4. Product Forecast'!E39,'4. Product Forecast'!E71)) | E12: =IF($B$5="S",'4. Product Forecast'!F7,IF($B$5="M",'4. Product Forecast'!F39,'4. Product Forecast'!F71)) | F12: =IF($B$5="S",'4. Product Forecast'!G7,IF($B$5="M",'4. Product Forecast'!G39,'4. Product Forecast'!G71)) | G12: =F12
A14: SAAS
A15: SaaS Revenue | B15: ='5. P&L'!C7 | C15: ='5. P&L'!D7 | D15: ='5. P&L'!E7 | E15: ='5. P&L'!F7 | F15: ='5. P&L'!G7 | G15: =SUM(B15:F15)
A16: SaaS Costs | B16: ='5. P&L'!C11 | C16: ='5. P&L'!D11 | D16: ='5. P&L'!E11 | E16: ='5. P&L'!F11 | F16: ='5. P&L'!G11 | G16: =SUM(B16:F16)
A17: SaaS Gross Profit | B17: ='5. P&L'!C13 | C17: ='5. P&L'!D13 | D17: ='5. P&L'!E13 | E17: ='5. P&L'!F13 | F17: ='5. P&L'!G13 | G17: =SUM(B17:F17)
A18: SaaS Margin | B18: ='5. P&L'!C14 | C18: ='5. P&L'!D14 | D18: ='5. P&L'!E14 | E18: ='5. P&L'!F14 | F18: ='5. P&L'!G14 | G18: =IF(G15>0,G17/G15,0)
A20: HARDWARE
A21: Hardware Revenue | B21: ='5. P&L'!C17 | C21: ='5. P&L'!D17 | D21: ='5. P&L'!E17 | E21: ='5. P&L'!F17 | F21: ='5. P&L'!G17 | G21: =SUM(B21:F21)
A22: Hardware COGS | B22: ='5. P&L'!C21 | C22: ='5. P&L'!D21 | D22: ='5. P&L'!E21 | E22: ='5. P&L'!F21 | F22: ='5. P&L'!G21 | G22: =SUM(B22:F22)
A23: Hardware Gross Profit | B23: ='5. P&L'!C23 | C23: ='5. P&L'!D23 | D23: ='5. P&L'!E23 | E23: ='5. P&L'!F23 | F23: ='5. P&L'!G23 | G23: =SUM(B23:F23)
A24: Hardware Margin | B24: ='5. P&L'!C24 | C24: ='5. P&L'!D24 | D24: ='5. P&L'!E24 | E24: ='5. P&L'!F24 | F24: ='5. P&L'!G24 | G24: =IF(G21>0,G23/G21,0)
A25: Founder Seed / Operating Cash (NOT LSC investment) | B25: ='6. Cash Flow'!C7 | C25: ← Cash Flow opening cash; LSC equity investment shown only when LSC sheets unhidden
A26: COMBINED | B26: =G22
A27: Total Revenue | B27: ='5. P&L'!C27 | C27: ='5. P&L'!D27 | D27: ='5. P&L'!E27 | E27: ='5. P&L'!F27 | F27: ='5. P&L'!G27 | G27: =SUM(B27:F27)
A28: Total Costs | B28: ='5. P&L'!C28 | C28: ='5. P&L'!D28 | D28: ='5. P&L'!E28 | E28: ='5. P&L'!F28 | F28: ='5. P&L'!G28 | G28: =SUM(B28:F28)
A29: Total Gross Profit | B29: ='5. P&L'!C30 | C29: ='5. P&L'!D30 | D29: ='5. P&L'!E30 | E29: ='5. P&L'!F30 | F29: ='5. P&L'!G30 | G29: =SUM(B29:F29)
A30: Blended Margin | B30: ='5. P&L'!C31 | C30: ='5. P&L'!D31 | D30: ='5. P&L'!E31 | E30: ='5. P&L'!F31 | F30: ='5. P&L'!G31 | G30: =IF(G27>0,G29/G27,0)
B32: REVENUE MIX (Y5 — selected scenario)
B33: Three-way breakout shows what gets premium SaaS multiples vs hardware multiples.
B35: Line | C35: Y5 ($) | D35: % of Total | E35: Multiple (Base) | F35: Y5 Exit Value
B36: Standard Cloud SaaS | C36: ='5. P&L'!G8 | D36: =C36/$C$39 | E36: 10 | F36: =C36*E36
B37: ACaaS (panel-attached) | C37: ='5. P&L'!G9 | D37: =C37/$C$39 | E37: 6 | F37: =C37*E37
B38: Hardware (locks + panels) | C38: ='5. P&L'!G17 | D38: =C38/$C$39 | E38: 1.5 | F38: =C38*E38
B39: Total Y5 Revenue | C39: =SUM(C36:C38) | D39: =SUM(D36:D38) | F39: =SUM(F36:F38)
B41: Notes:
B42: • Standard SaaS = pure software (Cloud Base, Access, Rooms, Lockers, Integrate, Booking) — premium 8-12x ARR multiple
B43: • ACaaS = panel-attached recurring (Hardware-driven SaaS) — 5-7x ARR (Brivo/Openpath precedent)
B44: • Hardware = locks + panels gross — commodity 1-2x revenue, separate margin

Sheet 3. Assumptions
A1: ASSUMPTIONS — Zezamii Cloud
A2: Yellow cells = editable inputs
A4: CLOUD PLATFORM PRICING (Annual)
A5: Small | B5: 750
A6: Medium | B6: 1100
A7: Large | B7: 1650
A8: Enterprise | B8: 3500
A10: MODULE PRICING
A11: Credential Pack (50-pack/year) | B11: 100 | C11: First 10 included in Cloud tier
A12: Rooms (per room/month) | B12: 8
A13: Lockers (per locker/month) | B13: 4
A14: Integrate (per integration/year) | B14: 2000
A15: Booking (% of transaction) | B15: 0.025
A16: Avg Booking Transaction Value ($) | B16: 40 | C16: Net to Zezamii per txn = this × take rate (B15) = $1.00
A17: HARDWARE
A18: Lock RETAIL price (Zezamii to customer) | B18: 420 | C18: Sticker price end customer pays
A19: Locks per Booking Site | B19: 1 | C19: 1 lock per booking sale (entry/access lock)
A20: PARTNER MARGIN
A21: Partner Margin (% off retail) | B21: 0.35 | C21: Was 5-tier (Plat/Gold/Silver/Bronze/Retail); simplified to single rate. Was 15% Silver default.
A22: Zezamii Hardware Margin % (input) | B22: 0.25 | C22: What Zezamii keeps from retail. Definite — this is the negotiated Zezamii take.
A23: LSC + Mfr Combined % (derived) | B23: =1-B22 | C23: What Zezamii pays LSC (LSC's revenue per lock incl. Mfr cost passed through)
A24: (Zezamii GM = B22, this row deprecated) | B24: =B22
A25: (Mfr landed cost — informational only, not used) | B25: 140 | C25: Informational reference only. Mfr/LSC split not modeled. Zezamii pays LSC at B26.
A26: Lock — LSC sell-in price to Zezamii (= Zezamii COGS per lock) | B26: =B18*(1-B22) | C26: Derived = Retail × (1 − Zezamii margin %). This IS the COGS that hits Zezamii's P&L.
A27: (LSC margin implied — informational only) | B27: =B26-B25 | C27: Informational only. Drops out of model.
A28: S (Conservative) - Year 1 | B28: 28 | C28: Realistic v16 (Y1=62 to clear 250K w S attach rates)
A29: M (Base Case) - Year 1 | B29: 29 | C29: Realistic v12 (M pulled down)
A30: L (Aggressive) - Year 1 | B30: 61 | C30: Realistic v10 (target ~3120 active Y5)
A31: S - Growth Multiplier (Year 2+) | B31: 1.6 | C31: Realistic (was 1.5)
A32: M - Growth Multiplier (Year 2+) | B32: 1.85 | C32: Realistic v12
A33: L - Growth Multiplier (Year 2+) | B33: 2 | C33: Realistic v10
A34: OTHER ASSUMPTIONS
A35: Annual Churn Rate | B35: 0.05
A36: Salary Escalation (annual) | B36: 0.04
A37: Price Escalation (annual) | B37: 0.05
A38: Implied B2B Locks (link to B46) | B38: =B46
A39: CURRENT STATE
A40: Existing Sites (Year 0) | B40: 30
A41: Existing ARR (Year 0) | B41: 139000 | C41: FY26 actual own-software recurring (Cloud+Rooms+Lockers+Vortex+Zezamii; excl $202k Verkada resale). Was $120k.
A42: Convertible Sites Y0 (see B50) | B42: =B50
A43: LSC INSTALLED BASE
A44: Total LSC Locks Deployed | B44: 50000
A45: % B2B (Builders/SMB) | B45: 0.25 | C45: How much Zezamii accelerates LSC lock sales
A46: Implied B2B Locks | B46: =B44*B45
A47: Avg Locks per Site | B47: 35
A48: Implied B2B Sites (LSC Base) | B48: =ROUND(B46/B47,0)
A49: Conversion Rate (Year 1-2) | B49: 0.2
A50: Convertible Sites | B50: =ROUND(B48*B49,0) | C50: Year ACaaS becomes available
A51: ACaaS ARR per Site | B51: 6250
A52: LSC ACCELERANT EFFECT
A53: Zezamii Lock Sales Uplift % | B53: 0.25
A54: Avg Lock Price (to LSC customer, = B18 retail) | B54: ='3. Assumptions'!B18
A55: LSC Margin on Lock | B55: 0.35
A56: (removed: duplicate of B64)
A57: ACaaS (INTEGRATED PANEL) | C57: 100% of target
A58: Launch Year | B58: 2
A59: ACaaS ARR per Site | B59: 6250
A60: % New Sites Taking ACaaS (Y2+, scenario-aware → B92/C92/D92) | B60: =IF('2. Dashboard'!$B$5="S",$B$92,IF('2. Dashboard'!$B$5="M",$C$92,$D$92)) | C60: Now wired: S=10% / M=25% / L=40% via B92:D92
A61: Panels per ACaaS Site | B61: 1.5
A62: Panel Price | B62: 2500
A63: LSC Panel Margin | B63: 0.35
A64: ACaaS Ramp (Year 2) | B64: 0.5 | C64: 50% of target in launch year
A65: ACaaS Ramp (Year 3+) | B65: 1 | C65: 100% of target
A67: COST SCALING (Min Opex % of Revenue)
A68: Year 1 Min Opex % | B68: 0.45 | C68: Investment phase → 55% SaaS margin
A69: Year 2 Min Opex % | B69: 0.38 | C69: Scaling up → 62% SaaS margin
A70: Year 3 Min Opex % | B70: 0.32 | C70: Growth mode → 68% SaaS margin
A71: Year 4 Min Opex % | B71: 0.28 | C71: Scale → 72% SaaS margin
A72: Year 5 Min Opex % | B72: 0.25 | C72: Efficient → 75% SaaS margin
A74: INVESTMENT BY TEAM MODEL
A75: Product Investment | B75: 500000
A76: Zezamii Investment | B76: 750000
A77: Zezamii LSC Investment | B77: 1100000
A79: LSC CHANNEL MIX (% of SaaS revenue via LSC)
A80: Year 1 | B80: 0.7 | C80: Ramping LSC partnership penetration
A81: Year 2 | B81: 0.75
A82: Year 3 | B82: 0.8
A83: Year 4 | B83: 0.85
A84: Year 5 | B84: 0.85
A86: (Module attach rates removed — Product Forecast drives units directly now)
A91: ACaaS Take-up % by Scenario (used by B60) | B91: S | C91: M | D91: L
B92: 0.1 | C92: 0.25 | D92: 0.4 | E92: ← S/M/L take-up of new sites adopting ACaaS in launch year and onwards
A94: Alt Channel Capture % (if ACaaS off — digital locks + integrations) | B94: 0.65 | C94: When ACaaS toggle (Dashboard B6) = No, this % of the ACaaS revenue line is retained via alternative channels (digital lock upsell + access control integrations). Panels (hardware) drop to zero in this path.
A95: PIPELINE & CAPACITY BRIDGE — explains M-scenario site adds vs LSC base
A96: LSC convertible base (B2B installed) | B96: =B50 | C96: sites
A97: Conversion rate (Y1-Y2 target) | B97: 0.5 | C97: % of convertible base
A98: → LSC-channel addressable Y1-Y2 | B98: =B96*B97 | C98: sites
A99: Non-LSC channel (direct + builder partners) | B99: 50 | C99: sites — placeholder, confirm
A100: → Total addressable Y1-Y2 | B100: =B98+B99 | C100: sites
A101: M scenario Y1-Y2 new sites needed | B101: =SUM(Revenue!C5:D5) | C101: from Revenue tab
A102: Capture rate vs total addressable | B102: =B101/B100 | C102: should be <100%
A103: Sales capacity (avg sales rep close rate) | B103: 4 | C103: sites/rep/month — placeholder
A104: → Sales capacity Y1-Y2 (1 rep × 24mo) | B104: =B103*24 | C104: sites
A105: Realism check: capacity ≥ needed? | B105: =IF(B104>=B101,"OK","GAP") | C105: flag
A110: DERIVED NET PRICES — after partner margin (auto, used by Product Forecast)
A111: Cloud Base blended net (tier mix × (1-partner margin)) | B111: =(0.4*B5+0.35*B6+0.2*B7+0.05*B8)*(1-B21) | C111: 40% Small + 35% Med + 20% Large + 5% Enterprise blend × 65%
A112: Access net (per pack/yr) | B112: =B11*(1-B21) | C112: =B11 * 65%
A113: Rooms net (per room/yr) | B113: =B12*12*(1-B21)
A114: Lockers net (per locker/yr) | B114: =B13*12*(1-B21) | C114: FLAG: Previously hardcoded as $23.40 (implied $3/mo, not B13=$4/mo). Refactor now uses B13 cleanly. If you want the old number, change B13 from $4 to $3.
A115: Integrate net (per integration/yr) | B115: =B14*(1-B21) | C115: =B14 * 65%
...

Sheet 4. Product Forecast
B2: PRODUCT FORECAST
B3: Type unit counts per product per year for each scenario. Revenue computed automatically. Yellow cells = editable.
B5: S + PRODUCT (no LSC) -- Y1=62 sites | 1.6x growth | Y5 active sites=920
C6: Y1 | D6: Y2 | E6: Y3 | F6: Y4 | G6: Y5 | H6: 5yr Cum
B7: Active sites (from Revenue tab) | C7: 85 | D7: 178 | E7: 324 | F7: 554 | G7: 920
B8: New sites added (from Revenue tab) | C8: 62 | D8: 99 | E8: 158 | F8: 253 | G8: 405 | H8: 977
B9: Y0 Baseline Retained ARR (churn 5% offset by 5% uplift) | C9: =Revenue!C19 | D9: =Revenue!D19 | E9: =Revenue!E19 | F9: =Revenue!F19 | G9: =Revenue!G19
B10: SaaS PRODUCTS (units + revenue)
B11: Cloud Base (sites) | C11: 40 | D11: 82 | E11: 127 | F11: 217 | G11: 347
B12: revenue ($, net) | C12: =C11*'3. Assumptions'!$B$111 | D12: =D11*'3. Assumptions'!$B$111 | E12: =E11*'3. Assumptions'!$B$111 | F12: =F11*'3. Assumptions'!$B$111 | G12: =G11*'3. Assumptions'!$B$111 | H12: =SUM(C12:G12)
B13: Access (packs) | C13: 22 | D13: 81 | E13: 137 | F13: 309 | G13: 546
B14: revenue ($, net) | C14: =C13*'3. Assumptions'!$B$112 | D14: =D13*'3. Assumptions'!$B$112 | E14: =E13*'3. Assumptions'!$B$112 | F14: =F13*'3. Assumptions'!$B$112 | G14: =G13*'3. Assumptions'!$B$112 | H14: =SUM(C14:G14)
B15: Rooms (rooms) | C15: 980 | D15: 1760 | E15: 3010 | F15: 4550 | G15: 6120
B16: revenue ($, net) | C16: =C15*'3. Assumptions'!$B$113 | D16: =D15*'3. Assumptions'!$B$113 | E16: =E15*'3. Assumptions'!$B$113 | F16: =F15*'3. Assumptions'!$B$113 | G16: =G15*'3. Assumptions'!$B$113 | H16: =SUM(C16:G16)
B17: Lockers (lockers) | C17: 900 | D17: 1400 | E17: 1890 | F17: 3200 | G17: 4990
B18: revenue ($, net) | C18: =C17*'3. Assumptions'!$B$114 | D18: =D17*'3. Assumptions'!$B$114 | E18: =E17*'3. Assumptions'!$B$114 | F18: =F17*'3. Assumptions'!$B$114 | G18: =G17*'3. Assumptions'!$B$114 | H18: =SUM(C18:G18)
B19: Integrate (integrations) | C19: 4 | D19: 10 | E19: 18 | F19: 25 | G19: 30
B20: revenue ($, net) | C20: =C19*'3. Assumptions'!$B$115 | D20: =D19*'3. Assumptions'!$B$115 | E20: =E19*'3. Assumptions'!$B$115 | F20: =F19*'3. Assumptions'!$B$115 | G20: =G19*'3. Assumptions'!$B$115 | H20: =SUM(C20:G20)
B21: Booking Sites (bundle: 1× Cloud S license + 2.5% txn fee) | C21: 12 | D21: 65 | E21: 110 | F21: 279 | G21: 376
B22: revenue ($, net) — license + txn | C22: =C21*('3. Assumptions'!$B$5*(1-'3. Assumptions'!$B$21)+100*'3. Assumptions'!$B$16*'3. Assumptions'!$B$15) | D22: =D21*('3. Assumptions'!$B$5*(1-'3. Assumptions'!$B$21)+150*'3. Assumptions'!$B$16*'3. Assumptions'!$B$15) | E22: =E21*('3. Assumptions'!$B$5*(1-'3. Assumptions'!$B$21)+200*'3. Assumptions'!$B$16*'3. Assumptions'!$B$15) | F22: =F21*('3. Assumptions'!$B$5*(1-'3. Assumptions'!$B$21)+250*'3. Assumptions'!$B$16*'3. Assumptions'!$B$15) | G22: =G21*('3. Assumptions'!$B$5*(1-'3. Assumptions'!$B$21)+300*'3. Assumptions'!$B$16*'3. Assumptions'!$B$15) | H22: =SUM(C22:G22)
B23: ACaaS sites (or Alt: digital locks + integrations @ 65% — see B6 toggle) | C23: =IF('2. Dashboard'!$B$6="Yes",9,9*'3. Assumptions'!$B$94) | D23: =IF('2. Dashboard'!$B$6="Yes",27,27*'3. Assumptions'!$B$94) | E23: =IF('2. Dashboard'!$B$6="Yes",85,85*'3. Assumptions'!$B$94) | F23: =IF('2. Dashboard'!$B$6="Yes",157,157*'3. Assumptions'!$B$94) | G23: =IF('2. Dashboard'!$B$6="Yes",313,313*'3. Assumptions'!$B$94)
B24: revenue ($, net) | C24: =C23*'3. Assumptions'!$B$116 | D24: =D23*'3. Assumptions'!$B$116 | E24: =E23*'3. Assumptions'!$B$116 | F24: =F23*'3. Assumptions'!$B$116 | G24: =G23*'3. Assumptions'!$B$116 | H24: =SUM(C24:G24)
B25: SaaS Subtotal (new sites, excl. Y0 retention, excl. ACaaS) | C25: =C12+C14+C16+C18+C20+C22 | D25: =D12+D14+D16+D18+D20+D22 | E25: =E12+E14+E16+E18+E20+E22 | F25: =F12+F14+F16+F18+F20+F22 | G25: =G12+G14+G16+G18+G20+G22 | H25: =SUM(C25:G25)
B26: Total Retained ARR Base (incl. all prior cohorts, after churn & uplift) | C26: ='3. Assumptions'!$B$41*(1-'3. Assumptions'!$B$35)*(1+'3. Assumptions'!$B$37) | D26: =(C26+C25+C24)*(1-'3. Assumptions'!$B$35)*(1+'3. Assumptions'!$B$37) | E26: =(D26+D25+D24)*(1-'3. Assumptions'!$B$35)*(1+'3. Assumptions'!$B$37) | F26: =(E26+E25+E24)*(1-'3. Assumptions'!$B$35)*(1+'3. Assumptions'!$B$37) | G26: =(F26+F25+F24)*(1-'3. Assumptions'!$B$35)*(1+'3. Assumptions'!$B$37)
B27: HARDWARE PRODUCTS (units + revenue)
B28: HW Locks (base + 1 lock per booking site) | C28: =449+C21*'3. Assumptions'!$B$19 | D28: =950+D21*'3. Assumptions'!$B$19 | E28: =1399+E21*'3. Assumptions'!$B$19 | F28: =2226+F21*'3. Assumptions'!$B$19 | G28: =3563+G21*'3. Assumptions'!$B$19
B29: revenue ($, gross) | C29: =C28*'3. Assumptions'!$B$18 | D29: =D28*'3. Assumptions'!$B$18 | E29: =E28*'3. Assumptions'!$B$18 | F29: =F28*'3. Assumptions'!$B$18 | G29: =G28*'3. Assumptions'!$B$18 | H29: =SUM(C29:G29)
B30: HW Panels (panels) | C30: =IF('2. Dashboard'!$B$6="Yes",13,0) | D30: =IF('2. Dashboard'!$B$6="Yes",27,0) | E30: =IF('2. Dashboard'!$B$6="Yes",87,0) | F30: =IF('2. Dashboard'!$B$6="Yes",107,0) | G30: =IF('2. Dashboard'!$B$6="Yes",235,0)
B31: revenue ($, gross) | C31: =C30*'3. Assumptions'!$B$117 | D31: =D30*'3. Assumptions'!$B$117 | E31: =E30*'3. Assumptions'!$B$117 | F31: =F30*'3. Assumptions'!$B$117 | G31: =G30*'3. Assumptions'!$B$117 | H31: =SUM(C31:G31)
B32: Hardware Subtotal | C32: =C29+C31 | D32: =D29+D31 | E32: =E29+E31 | F32: =F29+F31 | G32: =G29+G31 | H32: =SUM(C32:G32)
B34: TOTAL REVENUE | C34: =C25+C32 | D34: =D25+D32 | E34: =E25+E32 | F34: =F25+F32 | G34: =G25+G32 | H34: =SUM(C34:G34)
B37: M + ZEZAMII (modest LSC) -- Y1=70 sites | 1.85x growth | Y5 active sites=1622
C38: Y1 | D38: Y2 | E38: Y3 | F38: Y4 | G38: Y5 | H38: 5yr Cum
B39: Active sites (from Revenue tab) | C39: 93 | D39: 216 | E39: 442 | F39: 857 | G39: 1622
B40: New sites added (from Revenue tab) | C40: 70 | D40: 130 | E40: 241 | F40: 446 | G40: 825 | H40: 1712
B41: Y0 Baseline Retained ARR (churn 5% offset by 5% uplift) | C41: =Revenue!C19 | D41: =Revenue!D19 | E41: =Revenue!E19 | F41: =Revenue!F19 | G41: =Revenue!G19
B42: SaaS PRODUCTS (units + revenue)
B43: Cloud Base (sites) | C43: 60 | D43: 122 | E43: 182 | F43: 393 | G43: 782
B44: revenue ($, net) | C44: =C43*'3. Assumptions'!$B$111 | D44: =D43*'3. Assumptions'!$B$111 | E44: =E43*'3. Assumptions'!$B$111 | F44: =F43*'3. Assumptions'!$B$111 | G44: =G43*'3. Assumptions'!$B$111 | H44: =SUM(C44:G44)
B45: Access (packs) | C45: 41 | D45: 103 | E45: 215 | F45: 401 | G45: 806
B46: revenue ($, net) | C46: =C45*'3. Assumptions'!$B$112 | D46: =D45*'3. Assumptions'!$B$112 | E46: =E45*'3. Assumptions'!$B$112 | F46: =F45*'3. Assumptions'!$B$112 | G46: =G45*'3. Assumptions'!$B$112 | H46: =SUM(C46:G46)
B47: Rooms (rooms) | C47: 1760 | D47: 3020 | E47: 4990 | F47: 6671 | G47: 11092
B48: revenue ($, net) | C48: =C47*'3. Assumptions'!$B$113 | D48: =D47*'3. Assumptions'!$B$113 | E48: =E47*'3. Assumptions'!$B$113 | F48: =F47*'3. Assumptions'!$B$113 | G48: =G47*'3. Assumptions'!$B$113 | H48: =SUM(C48:G48)
B49: Lockers (lockers) | C49: 1400 | D49: 2500 | E49: 3890 | F49: 5110 | G49: 7220
B50: revenue ($, net) | C50: =C49*'3. Assumptions'!$B$114 | D50: =D49*'3. Assumptions'!$B$114 | E50: =E49*'3. Assumptions'!$B$114 | F50: =F49*'3. Assumptions'!$B$114 | G50: =G49*'3. Assumptions'!$B$114 | H50: =SUM(C50:G50)
B51: Integrate (integrations) | C51: 8 | D51: 17 | E51: 36 | F51: 46 | G51: 70
B52: revenue ($, net) | C52: =C51*'3. Assumptions'!$B$115 | D52: =D51*'3. Assumptions'!$B$115 | E52: =E51*'3. Assumptions'!$B$115 | F52: =F51*'3. Assumptions'!$B$115 | G52: =G51*'3. Assumptions'!$B$115 | H52: =SUM(C52:G52)
B53: Booking Sites (bundle: 1× Cloud S license + 2.5% txn fee) | C53: 22 | D53: 89 | E53: 148 | F53: 322 | G53: 511
B54: revenue ($, net) — license + txn | C54: =C53*('3. Assumptions'!$B$5*(1-'3. Assumptions'!$B$21)+100*'3. Assumptions'!$B$16*'3. Assumptions'!$B$15) | D54: =D53*('3. Assumptions'!$B$5*(1-'3. Assumptions'!$B$21)+150*'3. Assumptions'!$B$16*'3. Assumptions'!$B$15) | E54: =E53*('3. Assumptions'!$B$5*(1-'3. Assumptions'!$B$21)+200*'3. Assumptions'!$B$16*'3. Assumptions'!$B$15) | F54: =F53*('3. Assumptions'!$B$5*(1-'3. Assumptions'!$B$21)+250*'3. Assumptions'!$B$16*'3. Assumptions'!$B$15) | G54: =G53*('3. Assumptions'!$B$5*(1-'3. Assumptions'!$B$21)+300*'3. Assumptions'!$B$16*'3. Assumptions'!$B$15) | H54: =SUM(C54:G54)
B55: ACaaS sites (or Alt: digital locks + integrations @ 65% — see B6 toggle) | C55: =IF('2. Dashboard'!$B$6="Yes",21,21*'3. Assumptions'!$B$94) | D55: =IF('2. Dashboard'!$B$6="Yes",62,62*'3. Assumptions'!$B$94) | E55: =IF('2. Dashboard'!$B$6="Yes",196,196*'3. Assumptions'!$B$94) | F55: =IF('2. Dashboard'!$B$6="Yes",362,362*'3. Assumptions'!$B$94) | G55: =IF('2. Dashboard'!$B$6="Yes",724,724*'3. Assumptions'!$B$94)
B56: revenue ($, net) | C56: =C55*'3. Assumptions'!$B$116 | D56: =D55*'3. Assumptions'!$B$116 | E56: =E55*'3. Assumptions'!$B$116 | F56: =F55*'3. Assumptions'!$B$116 | G56: =G55*'3. Assumptions'!$B$116 | H56: =SUM(C56:G56)
B57: SaaS Subtotal (new sites, excl. Y0 retention, excl. ACaaS) | C57: =C44+C46+C48+C50+C52+C54 | D57: =D44+D46+D48+D50+D52+D54 | E57: =E44+E46+E48+E50+E52+E54 | F57: =F44+F46+F48+F50+F52+F54 | G57: =G44+G46+G48+G50+G52+G54 | H57: =SUM(C57:G57)
B58: Total Retained ARR Base (incl. all prior cohorts, after churn & uplift) | C58: ='3. Assumptions'!$B$41*(1-'3. Assumptions'!$B$35)*(1+'3. Assumptions'!$B$37) | D58: =(C58+C57+C56)*(1-'3. Assumptions'!$B$35)*(1+'3. Assumptions'!$B$37) | E58: =(D58+D57+D56)*(1-'3. Assumptions'!$B$35)*(1+'3. Assumptions'!$B$37) | F58: =(E58+E57+E56)*(1-'3. Assumptions'!$B$35)*(1+'3. Assumptions'!$B$37) | G58: =(F58+F57+F56)*(1-'3. Assumptions'!$B$35)*(1+'3. Assumptions'!$B$37)
B59: HARDWARE PRODUCTS (units + revenue)
B60: HW Locks (base + 1 lock per booking site) | C60: =1036+C53*'3. Assumptions'!$B$19 | D60: =2194+D53*'3. Assumptions'!$B$19 | E60: =3229+E53*'3. Assumptions'!$B$19 | F60: =5139+F53*'3. Assumptions'!$B$19 | G60: =8227+G53*'3. Assumptions'!$B$19
B61: revenue ($, gross) | C61: =C60*'3. Assumptions'!$B$18 | D61: =D60*'3. Assumptions'!$B$18 | E61: =E60*'3. Assumptions'!$B$18 | F61: =F60*'3. Assumptions'!$B$18 | G61: =G60*'3. Assumptions'!$B$18 | H61: =SUM(C61:G61)
B62: HW Panels (panels) | C62: =IF('2. Dashboard'!$B$6="Yes",31,0) | D62: =IF('2. Dashboard'!$B$6="Yes",62,0) | E62: =IF('2. Dashboard'!$B$6="Yes",202,0) | F62: =IF('2. Dashboard'!$B$6="Yes",248,0) | G62: =IF('2. Dashboard'!$B$6="Yes",543,0)
B63: revenue ($, gross) | C63: =C62*'3. Assumptions'!$B$117 | D63: =D62*'3. Assumptions'!$B$117 | E63: =E62*'3. Assumptions'!$B$117 | F63: =F62*'3. Assumptions'!$B$117 | G63: =G62*'3. Assumptions'!$B$117 | H63: =SUM(C63:G63)
B64: Hardware Subtotal | C64: =C61+C63 | D64: =D61+D63 | E64: =E61+E63 | F64: =F61+F63 | G64: =G61+G63 | H64: =SUM(C64:G64)
B66: TOTAL REVENUE | C66: =C57+C64 | D66: =D57+D64 | E66: =E57+E64 | F66: =F57+F64 | G66: =G57+G64 | H66: =SUM(C66:G66)
B69: L + LSC TEAM (full LSC) -- Y1=110 sites | 2.0x growth | Y5 active sites=3236
C70: Y1 | D70: Y2 | E70: Y3 | F70: Y4 | G70: Y5 | H70: 5yr Cum
B71: Active sites (from Revenue tab) | C71: 133 | D71: 344 | E71: 760 | F71: 1587 | G71: 3236
B72: New sites added (from Revenue tab) | C72: 110 | D72: 220 | E72: 440 | F72: 880 | G72: 1760 | H72: 3410
B73: Y0 Baseline Retained ARR (churn 5% offset by 5% uplift) | C73: =Revenue!C19 | D73: =Revenue!D19 | E73: =Revenue!E19 | F73: =Revenue!F19 | G73: =Revenue!G19
B74: SaaS PRODUCTS (units + revenue)
B75: Cloud Base (sites) | C75: 110 | D75: 223 | E75: 479 | F75: 898 | G75: 1579
B76: revenue ($, net) | C76: =C75*'3. Assumptions'!$B$111 | D76: =D75*'3. Assumptions'!$B$111 | E76: =E75*'3. Assumptions'!$B$111 | F76: =F75*'3. Assumptions'!$B$111 | G76: =G75*'3. Assumptions'!$B$111 | H76: =SUM(C76:G76)
B77: Access (packs) | C77: 82 | D77: 169 | E77: 327 | F77: 659 | G77: 1808
B78: revenue ($, net) | C78: =C77*'3. Assumptions'!$B$112 | D78: =D77*'3. Assumptions'!$B$112 | E78: =E77*'3. Assumptions'!$B$112 | F78: =F77*'3. Assumptions'!$B$112 | G78: =G77*'3. Assumptions'!$B$112 | H78: =SUM(C78:G78)
B79: Rooms (rooms) | C79: 2178 | D79: 4791 | E79: 7862 | F79: 12305 | G79: 18512
B80: revenue ($, net) | C80: =C79*'3. Assumptions'!$B$113 | D80: =D79*'3. Assumptions'!$B$113 | E80: =E79*'3. Assumptions'!$B$113 | F80: =F79*'3. Assumptions'!$B$113 | G80: =G79*'3. Assumptions'!$B$113 | H80: =SUM(C80:G80)
B81: Lockers (lockers) | C81: 1361 | D81: 2722 | E81: 4846 | F81: 9583 | G81: 13067
B82: revenue ($, net) | C82: =C81*'3. Assumptions'!$B$114 | D82: =D81*'3. Assumptions'!$B$114 | E82: =E81*'3. Assumptions'!$B$114 | F82: =F81*'3. Assumptions'!$B$114 | G82: =G81*'3. Assumptions'!$B$114 | H82: =SUM(C82:G82)
B83: Integrate (integrations) | C83: 22 | D83: 38 | E83: 71 | F83: 103 | G83: 120
B84: revenue ($, net) | C84: =C83*'3. Assumptions'!$B$115 | D84: =D83*'3. Assumptions'!$B$115 | E84: =E83*'3. Assumptions'!$B$115 | F84: =F83*'3. Assumptions'!$B$115 | G84: =G83*'3. Assumptions'!$B$115 | H84: =SUM(C84:G84)
B85: Booking Sites (bundle: 1× Cloud S license + 2.5% txn fee) | C85: 42 | D85: 111 | E85: 298 | F85: 511 | G85: =ROUND(G71*0.3,0)
B86: revenue ($, net) — license + txn | C86: =C85*('3. Assumptions'!$B$5*(1-'3. Assumptions'!$B$21)+100*'3. Assumptions'!$B$16*'3. Assumptions'!$B$15) | D86: =D85*('3. Assumptions'!$B$5*(1-'3. Assumptions'!$B$21)+150*'3. Assumptions'!$B$16*'3. Assumptions'!$B$15) | E86: =E85*('3. Assumptions'!$B$5*(1-'3. Assumptions'!$B$21)+200*'3. Assumptions'!$B$16*'3. Assumptions'!$B$15) | F86: =F85*('3. Assumptions'!$B$5*(1-'3. Assumptions'!$B$21)+250*'3. Assumptions'!$B$16*'3. Assumptions'!$B$15) | G86: =G85*('3. Assumptions'!$B$5*(1-'3. Assumptions'!$B$21)+300*'3. Assumptions'!$B$16*'3. Assumptions'!$B$15) | H86: =SUM(C86:G86)
B87: ACaaS sites (or Alt: digital locks + integrations @ 65% — see B6 toggle) | C87: =IF('2. Dashboard'!$B$6="Yes",54,54*'3. Assumptions'!$B$94) | D87: =IF('2. Dashboard'!$B$6="Yes",163,163*'3. Assumptions'!$B$94) | E87: =IF('2. Dashboard'!$B$6="Yes",517,517*'3. Assumptions'!$B$94) | F87: =IF('2. Dashboard'!$B$6="Yes",953,953*'3. Assumptions'!$B$94) | G87: =IF('2. Dashboard'!$B$6="Yes",1906,1906*'3. Assumptions'!$B$94)
B88: revenue ($, net) | C88: =C87*'3. Assumptions'!$B$116 | D88: =D87*'3. Assumptions'!$B$116 | E88: =E87*'3. Assumptions'!$B$116 | F88: =F87*'3. Assumptions'!$B$116 | G88: =G87*'3. Assumptions'!$B$116 | H88: =SUM(C88:G88)
B89: SaaS Subtotal (new sites, excl. Y0 retention, excl. ACaaS) | C89: =C76+C78+C80+C82+C84+C86 | D89: =D76+D78+D80+D82+D84+D86 | E89: =E76+E78+E80+E82+E84+E86 | F89: =F76+F78+F80+F82+F84+F86 | G89: =G76+G78+G80+G82+G84+G86 | H89: =SUM(C89:G89)
B90: Total Retained ARR Base (incl. all prior cohorts, after churn & uplift) | C90: ='3. Assumptions'!$B$41*(1-'3. Assumptions'!$B$35)*(1+'3. Assumptions'!$B$37) | D90: =(C90+C89+C88)*(1-'3. Assumptions'!$B$35)*(1+'3. Assumptions'!$B$37) | E90: =(D90+D89+D88)*(1-'3. Assumptions'!$B$35)*(1+'3. Assumptions'!$B$37) | F90: =(E90+E89+E88)*(1-'3. Assumptions'!$B$35)*(1+'3. Assumptions'!$B$37) | G90: =(F90+F89+F88)*(1-'3. Assumptions'!$B$35)*(1+'3. Assumptions'!$B$37)
B91: HARDWARE PRODUCTS (units + revenue)
B92: HW Locks (base + 1 lock per booking site) | C92: =2728+C85*'3. Assumptions'!$B$19 | D92: =5777+D85*'3. Assumptions'!$B$19 | E92: =8505+E85*'3. Assumptions'!$B$19 | F92: =13533+F85*'3. Assumptions'!$B$19 | G92: =21665+G85*'3. Assumptions'!$B$19
B93: revenue ($, gross) | C93: =C92*'3. Assumptions'!$B$18 | D93: =D92*'3. Assumptions'!$B$18 | E93: =E92*'3. Assumptions'!$B$18 | F93: =F92*'3. Assumptions'!$B$18 | G93: =G92*'3. Assumptions'!$B$18 | H93: =SUM(C93:G93)
B94: HW Panels (panels) | C94: =IF('2. Dashboard'!$B$6="Yes",82,0) | D94: =IF('2. Dashboard'!$B$6="Yes",163,0) | E94: =IF('2. Dashboard'!$B$6="Yes",531,0) | F94: =IF('2. Dashboard'!$B$6="Yes",653,0) | G94: =IF('2. Dashboard'!$B$6="Yes",1429,0)
B95: revenue ($, gross) | C95: =C94*'3. Assumptions'!$B$117 | D95: =D94*'3. Assumptions'!$B$117 | E95: =E94*'3. Assumptions'!$B$117 | F95: =F94*'3. Assumptions'!$B$117 | G95: =G94*'3. Assumptions'!$B$117 | H95: =SUM(C95:G95)
B96: Hardware Subtotal | C96: =C93+C95 | D96: =D93+D95 | E96: =E93+E95 | F96: =F93+F95 | G96: =G93+G95 | H96: =SUM(C96:G96)
B98: TOTAL REVENUE | C98: =C89+C96 | D98: =D89+D96 | E98: =E89+E96 | F98: =F89+F96 | G98: =G89+G96 | H98: =SUM(C98:G98)
B102: NOTES
B103: PRICING NOTE:
B104: All per-unit prices now read from Assumptions sheet DERIVED NET PRICES (B111-B118). Change once in Assumptions, propagates across all scenarios.
B105: Active sites / new sites pulled from Revenue tab (driven by Growth Scenario inputs).
B106: Active sites / new sites pulled from Revenue tab (driven by Growth Scenario inputs in Assumptions).
B107: Edit any yellow unit cell to override the seeded value. Revenue updates instantly.
B108: SaaS Subtotal (excl ACaaS) and Hardware Subtotal flow into Revenue/P&L per Dashboard scenario.
B109: ACaaS revenue stays on its existing pipeline (Revenue!C70) — listed here for visibility but not double-counted.

Sheet 5. P&L
A1: PROFIT & LOSS
A2: Zezamii Cloud — SaaS & Hardware Breakdown
B3: Segment view: | D3: Standard SaaS | E3: ↓ jump to segment detail (rows 40-52)
C4: Year 1 | D4: Year 2 | E4: Year 3 | F4: Year 4 | G4: Year 5 | I4: 5-Year Total
B5: =D3 & " selected:" | C5: =IF($D$3="Combined",C27,IF($D$3="Standard SaaS",C8,IF($D$3="ACaaS",C9,C17))) | D5: =IF($D$3="Combined",D27,IF($D$3="Standard SaaS",D8,IF($D$3="ACaaS",D9,D17))) | E5: =IF($D$3="Combined",E27,IF($D$3="Standard SaaS",E8,IF($D$3="ACaaS",E9,E17))) | F5: =IF($D$3="Combined",F27,IF($D$3="Standard SaaS",F8,IF($D$3="ACaaS",F9,F17))) | G5: =IF($D$3="Combined",G27,IF($D$3="Standard SaaS",G8,IF($D$3="ACaaS",G9,G17))) | H5: =SUM(C5:G5)
A6: SAAS BUSINESS
A7: SaaS Revenue | C7: =C8+C9 | D7: =D8+D9 | E7: =E8+E9 | F7: =F8+F9 | G7: =G8+G9 | I7: =SUM(C7:G7)
A8: Standard Cloud | C8: =Revenue!C25 | D8: =Revenue!D25 | E8: =Revenue!E25 | F8: =Revenue!F25 | G8: =Revenue!G25 | I8: =SUM(C8:G8)
A9: ACaaS (Panel) | C9: =Revenue!C70 | D9: =Revenue!D70 | E9: =Revenue!E70 | F9: =Revenue!F70 | G9: =Revenue!G70 | I9: =SUM(C9:G9)
A11: SaaS Operating Costs | C11: ='Team Summary'!B22 | D11: ='Team Summary'!C22 | E11: ='Team Summary'!D22 | F11: ='Team Summary'!E22 | G11: ='Team Summary'!F22 | I11: =SUM(C11:G11)
A13: SaaS Contribution (Rev − SaaS Opex incl. team/infra) | C13: =C7-C11 | D13: =D7-D11 | E13: =E7-E11 | F13: =F7-F11 | G13: =G7-G11 | I13: =SUM(C13:G13)
A14: SaaS Contribution Margin % | C14: =IF(C7>0,C13/C7,0) | D14: =IF(D7>0,D13/D7,0) | E14: =IF(E7>0,E13/E7,0) | F14: =IF(F7>0,F13/F7,0) | G14: =IF(G7>0,G13/G7,0) | I14: =IF(I7>0,I13/I7,0)
A15: (Not pure SaaS gross margin — includes team/infra opex)
A16: HARDWARE BUSINESS
A17: Hardware Revenue | C17: =C18+C19 | D17: =D18+D19 | E17: =E18+E19 | F17: =F18+F19 | G17: =G18+G19 | I17: =SUM(C17:G17)
A18: Lock Sales | C18: =Revenue!C82 | D18: =Revenue!D82 | E18: =Revenue!E82 | F18: =Revenue!F82 | G18: =Revenue!G82 | I18: =SUM(C18:G18)
A19: Panel Sales | C19: =Revenue!C83 | D19: =Revenue!D83 | E19: =Revenue!E83 | F19: =Revenue!F83 | G19: =Revenue!G83 | I19: =SUM(C19:G19)
A21: Hardware COGS (= what Zezamii pays LSC, 75% of retail) | B21: Hardware COGS (= what Zezamii pays LSC, 75% of retail) | C21: =C17*'3. Assumptions'!$B$23 | D21: =D17*'3. Assumptions'!$B$23 | E21: =E17*'3. Assumptions'!$B$23 | F21: =F17*'3. Assumptions'!$B$23 | G21: =G17*'3. Assumptions'!$B$23 | I21: =SUM(C21:G21)
A23: Hardware Gross Profit | B23: Zezamii Hardware Gross Profit | C23: =C17-C21 | D23: =D17-D21 | E23: =E17-E21 | F23: =F17-F21 | G23: =G17-G21 | I23: =SUM(C23:G23)
A24: Hardware Gross Margin | B24: Zezamii Hardware Gross Margin % | C24: =IF(C17>0,C23/C17,0) | D24: =IF(D17>0,D23/D17,0) | E24: =IF(E17>0,E23/E17,0) | F24: =IF(F17>0,F23/F17,0) | G24: =IF(G17>0,G23/G17,0) | I24: =IF(I17>0,I23/I17,0)
A26: COMBINED TOTALS
A27: Total Revenue | C27: =C7+C17 | D27: =D7+D17 | E27: =E7+E17 | F27: =F7+F17 | G27: =G7+G17 | I27: =SUM(C27:G27)
A28: Total Costs | C28: =C11+C21 | D28: =D11+D21 | E28: =E11+E21 | F28: =F11+F21 | G28: =G11+G21 | I28: =SUM(C28:G28)
A30: Total Gross Profit | C30: =C13+C23 | D30: =D13+D23 | E30: =E13+E23 | F30: =F13+F23 | G30: =G13+G23 | I30: =SUM(C30:G30)
A31: Blended Gross Margin | C31: =IF(C27>0,C30/C27,0) | D31: =IF(D27>0,D30/D27,0) | E31: =IF(E27>0,E30/E27,0) | F31: =IF(F27>0,F30/F27,0) | G31: =IF(G27>0,G30/G27,0) | I31: =IF(I27>0,I30/I27,0)
A33: KEY METRICS
A34: SaaS ARR Growth | D34: =IF(C7>0,(D7-C7)/C7,0) | E34: =IF(D7>0,(E7-D7)/D7,0) | F34: =IF(E7>0,(F7-E7)/E7,0) | G34: =IF(F7>0,(G7-F7)/F7,0)
A35: SaaS % of Revenue | C35: =IF(C27>0,C7/C27,0) | D35: =IF(D27>0,D7/D27,0) | E35: =IF(E27>0,E7/E27,0) | F35: =IF(F27>0,F7/F27,0) | G35: =IF(G27>0,G7/G27,0)
A36: SaaS % of Gross Profit | C36: =IF(C30>0,C13/C30,0) | D36: =IF(D30>0,D13/D30,0) | E36: =IF(E30>0,E13/E30,0) | F36: =IF(F30>0,F13/F30,0) | G36: =IF(G30>0,G13/G30,0)
A37: Cumulative Profit | C37: =C30 | D37: =C37+D30 | E37: =D37+E30 | F37: =E37+F30 | G37: =F37+G30
B40: ↓ SEGMENT DETAIL — same data as row 5 inline summary, with cost + contribution
B41: =IF(D3="Combined","COMBINED P&L — true blended view. Revenue includes all three lines; costs include SaaS opex (R11) and HW COGS (R21).","Operating costs (team, infra, founder time) are SHARED across SaaS lines and cannot be cleanly split. Hardware has real COGS (35%). See main P&L for combined view.")
C43: Year 1 | D43: Year 2 | E43: Year 3 | F43: Year 4 | G43: Year 5 | H43: 5-Yr Total
B44: Revenue | C44: =IF($D$3="Combined",C27,IF($D$3="Standard SaaS",C8,IF($D$3="ACaaS",C9,C17))) | D44: =IF($D$3="Combined",D27,IF($D$3="Standard SaaS",D8,IF($D$3="ACaaS",D9,D17))) | E44: =IF($D$3="Combined",E27,IF($D$3="Standard SaaS",E8,IF($D$3="ACaaS",E9,E17))) | F44: =IF($D$3="Combined",F27,IF($D$3="Standard SaaS",F8,IF($D$3="ACaaS",F9,F17))) | G44: =IF($D$3="Combined",G27,IF($D$3="Standard SaaS",G8,IF($D$3="ACaaS",G9,G17))) | H44: =SUM(C44:G44)
B45: % of total business | C45: =IFERROR(C44/C27,0) | D45: =IFERROR(D44/D27,0) | E45: =IFERROR(E44/E27,0) | F45: =IFERROR(F44/F27,0) | G45: =IFERROR(G44/G27,0) | H45: =IFERROR(H44/SUM(C27:G27),0)
B47: =IF(D3="Combined","Total Costs (SaaS opex + HW COGS)",IF(D3="Hardware","Hardware COGS (35%)","Directly attributable cost")) | C47: =IF($D$3="Combined",C28,IF($D$3="Hardware",C21,0)) | D47: =IF($D$3="Combined",D28,IF($D$3="Hardware",D21,0)) | E47: =IF($D$3="Combined",E28,IF($D$3="Hardware",E21,0)) | F47: =IF($D$3="Combined",F28,IF($D$3="Hardware",F21,0)) | G47: =IF($D$3="Combined",G28,IF($D$3="Hardware",G21,0)) | H47: =SUM(C47:G47)
B48: =IF(D3="Combined","",IF(D3="Hardware","",IF(OR(D3="Standard SaaS",D3="ACaaS")," (SaaS opex is global — see row 11 for combined SaaS opex)","")))
B50: =IF(D3="Combined","Gross Profit","Contribution before global opex") | C50: =C44-C47 | D50: =D44-D47 | E50: =E44-E47 | F50: =F44-F47 | G50: =G44-G47 | H50: =SUM(C50:G50)
B51: =IF(D3="Combined","Blended Gross Margin %",IF(D3="Hardware","Hardware Gross Margin %","Segment GM% n/a — opex is global")) | C51: =IF(OR($D$3="Combined",$D$3="Hardware"),IFERROR(C50/C44,0),"") | D51: =IF(OR($D$3="Combined",$D$3="Hardware"),IFERROR(D50/D44,0),"") | E51: =IF(OR($D$3="Combined",$D$3="Hardware"),IFERROR(E50/E44,0),"") | F51: =IF(OR($D$3="Combined",$D$3="Hardware"),IFERROR(F50/F44,0),"") | G51: =IF(OR($D$3="Combined",$D$3="Hardware"),IFERROR(G50/G44,0),"") | H51: =IF(OR(D3="Combined",D3="Hardware"),IFERROR(H50/H44,0),"")
B52: How to read: pick segment or "Combined" at D3. Combined gives the true P&L (Revenue R27, Costs R28, GP R30, Blended GM R31). Single segments show only what is directly attributable; SaaS opex is global and cannot be cleanly split.
B55: HARDWARE MARGIN DECOMPOSITION — who gets what
B56: Zezamii keeps 25% (definite). LSC + Mfr Combined = 75% (what Zezamii pays LSC).
B58: Party | C58: Y1 | D58: Y2 | E58: Y3 | F58: Y4 | G58: Y5 | H58: 5-Yr Total | I58: % of Retail
B59: Retail Hardware Revenue | C59: =C17 | D59: =D17 | E59: =E17 | F59: =F17 | G59: =G17 | H59: =SUM(C59:G59) | I59: 1
B60: LSC + Mfr Combined (paid to LSC by Zezamii) | C60: =C17*'3. Assumptions'!$B$23 | D60: =D17*'3. Assumptions'!$B$23 | E60: =E17*'3. Assumptions'!$B$23 | F60: =F17*'3. Assumptions'!$B$23 | G60: =G17*'3. Assumptions'!$B$23 | H60: =SUM(C60:G60) | I60: ='3. Assumptions'!B23
B62: Zezamii Hardware Margin (definite) | C62: =C17*'3. Assumptions'!$B$22 | D62: =D17*'3. Assumptions'!$B$22 | E62: =E17*'3. Assumptions'!$B$22 | F62: =F17*'3. Assumptions'!$B$22 | G62: =G17*'3. Assumptions'!$B$22 | H62: =SUM(C62:G62) | I62: ='3. Assumptions'!B22
B63: Tie-out (Combined + Zezamii vs Retail) | C63: =C60+C62-C59 | D63: =D60+D62-D59 | E63: =E60+E62-E59 | F63: =F60+F62-F59 | G63: =G60+G62-G59 | H63: =SUM(C63:G63)
B65: Zezamii P&L view: HW Revenue (R17, retail) − HW COGS (R21, 75% paid to LSC) = HW GP (R23, 25% Zezamii). LSC/Mfr split within the 75% is not modeled.

Sheet 6. Cash Flow
A1: CASH FLOW STATEMENT
A2: Zezamii Cloud — SaaS & Hardware Breakdown
C4: Year 1 | D4: Year 2 | E4: Year 3 | F4: Year 4 | G4: Year 5 | I4: Total
A6: OPENING POSITION
A7: Opening Cash | C7: 50000 | D7: =C30 | E7: =D30 | F7: =E30 | G7: =F30
A8: Investment Received | B8: Investment Received (LSC) | C8: ='8. LSC Investment'!C58 | D8: 0 | E8: 0 | F8: 0 | G8: 0 | I8: =SUM(C8:G8)
A10: SAAS CASH FLOWS
A11: SaaS Revenue | C11: ='5. P&L'!C7 | D11: ='5. P&L'!D7 | E11: ='5. P&L'!E7 | F11: ='5. P&L'!F7 | G11: ='5. P&L'!G7 | I11: =SUM(C11:G11)
A12: SaaS Operating Costs | C12: ='5. P&L'!C11 | D12: ='5. P&L'!D11 | E12: ='5. P&L'!E11 | F12: ='5. P&L'!F11 | G12: ='5. P&L'!G11 | I12: =SUM(C12:G12)
A13: SaaS Net Cash | C13: =C11-C12 | D13: =D11-D12 | E13: =E11-E12 | F13: =F11-F12 | G13: =G11-G12 | I13: =SUM(C13:G13)
A15: HARDWARE CASH FLOWS
A16: Hardware Revenue | C16: ='5. P&L'!C17 | D16: ='5. P&L'!D17 | E16: ='5. P&L'!E17 | F16: ='5. P&L'!F17 | G16: ='5. P&L'!G17 | I16: =SUM(C16:G16)
A17: Hardware COGS | C17: ='5. P&L'!C21 | D17: ='5. P&L'!D21 | E17: ='5. P&L'!E21 | F17: ='5. P&L'!F21 | G17: ='5. P&L'!G21 | I17: =SUM(C17:G17)
A18: Hardware Net Cash | C18: =C16-C17 | D18: =D16-D17 | E18: =E16-E17 | F18: =F16-F17 | G18: =G16-G17 | I18: =SUM(C18:G18)
A20: NET CASH FLOW
A21: SaaS Net Cash | C21: =C13 | D21: =D13 | E21: =E13 | F21: =F13 | G21: =G13 | I21: =SUM(C21:G21)
A22: Hardware Net Cash | C22: =C18 | D22: =D18 | E22: =E18 | F22: =F18 | G22: =G18 | I22: =SUM(C22:G22)
A23: Total Net Cash Flow | C23: =C21+C22 | D23: =D21+D22 | E23: =E21+E22 | F23: =F21+F22 | G23: =G21+G22 | I23: =SUM(C23:G23)
A25: CLOSING POSITION
A26: Cash Flow (before investment) | C26: =C23 | D26: =D23 | E26: =E23 | F26: =F23 | G26: =G23
A27: Investment | C27: =C8 | D27: =D8 | E27: =E8 | F27: =F8 | G27: =G8
A28: Net Movement | C28: =C26+C27 | D28: =D26+D27 | E28: =E26+E27 | F28: =F26+F27 | G28: =G26+G27
A30: Closing Cash | C30: =C7+C28 | D30: =D7+D28 | E30: =E7+E28 | F30: =F7+F28 | G30: =G7+G28
A31: Cash Flow Positive? | C31: =IF(C23>=0,"✓ Yes","✗ No") | D31: =IF(D23>=0,"✓ Yes","✗ No") | E31: =IF(E23>=0,"✓ Yes","✗ No") | F31: =IF(F23>=0,"✓ Yes","✗ No") | G31: =IF(G23>=0,"✓ Yes","✗ No")

Sheet 7. Valuation
B2: PRODUCTCO VALUATION — Comps + DCF + Strategic Premium
B3: Yellow=input. Green=link. Black=formula. Sources cited inline.
B5: COMPS REFERENCE TABLE (2026 market data)
B6: Benchmark | C6: Low | D6: Mid | E6: High | H6: Source
B7: Australian SaaS <$1M ARR (local buyers) | C7: 3 | D7: 3.75 | E7: 4.5 | H7: Digital Asset Brokers AU (2026)
B8: Australian SaaS $1M-$5M ARR (intl buyers) | C8: 5.5 | D8: 6.75 | E8: 8 | H8: Digital Asset Brokers AU (2026)
B9: Global private SaaS median (M&A) | C9: 3.3 | D9: 4.5 | E9: 6.2 | H9: Aventis Advisors 2015-2026
B10: ACaaS direct comps (recalibrated from PropTech) | C10: 6 | D10: 8 | E10: 10 | H10: Brivo 11x, Openpath ~10-11x (strategic), Verkada 5.8x (huge scale). Conservative=6x reflects pre-revenue execution risk discount.
B11: Premium metrics (NRR >110%, R40 >50) | C11: 7 | D11: 8.5 | E11: 10 | H11: Digital Asset Brokers AU (2026)
B13: ANZ vs Intl buyer discount | C13: 0.2 | D13: 0.25 | E13: 0.3 | H13: Australian buyer-only deals discount by 20-30%
B14: Discount rate (early-stage VC) | C14: 0.25 | D14: 0.3 | E14: 0.35 | H14: VC standard for growth-stage SaaS: 25-40%
B15: Strategic premium over financial value | C15: 0.15 | D15: 0.25 | E15: 0.35 | H15: Strategic buyers pay 15-35% over financial-only valuation
B17: REVENUE FORECAST (links to Cloud Model)
B18: Year 0 ARR (existing) | C18: 139000 | H18: FY26 actual own-software recurring ~$139k / 30 sites (corrects prior "$170k/25 sites")
B19: Year 5 SaaS ARR (selected scenario) | C19: ='5. P&L'!G7 | H19: From P&L, responds to Dashboard scenario
B20: Year 5 Total Revenue (SaaS + HW) | C20: ='5. P&L'!G27
B21: 5-Year Cumulative Gross Profit | C21: ='5. P&L'!I30
B22: Implied ARR CAGR (Y0 → Y5) | C22: =(C19/C18)^(1/5)-1 | H22: Compound annual growth rate of SaaS ARR
B23: Selected scenario | C23: ='2. Dashboard'!B5 | D23: ="("&IF('2. Dashboard'!B5="S","Conservative",IF('2. Dashboard'!B5="M","Base","Aggressive"))&")"
B25: FORWARD-MULTIPLE VALUATION (Y5 ARR × Multiple, discounted)
B26: Approach | C26: Conservative | D26: Base | E26: Aggressive
B27: ARR Exit Multiple (chosen) | C27: =C10 | D27: =D10 | E27: =E10 | H27: Default = PropTech vertical comps (row 10); editable above
B28: Y5 Exit Value (gross) | C28: =$C$19*C27 | D28: =$C$19*D27 | E28: =$C$19*E27
B29: ANZ Buyer Discount | C29: =E13 | D29: =D13 | E29: =C13
B30: Y5 Exit Value (post-ANZ adjustment) | C30: =C28*(1-C29) | D30: =D28*(1-D29) | E30: =E28*(1-E29)
B31: Discount Rate | C31: =E14 | D31: =D14 | E31: =C14
B32: Years to Exit | C32: 5 | D32: 5 | E32: 5
B33: PRE-MONEY (Financial only) | C33: =C30/(1+C31)^C32 | D33: =D30/(1+D31)^D32 | E33: =E30/(1+E31)^E32
B35: STRATEGIC PREMIUM — LSC-specific value capture
B36: LSC strategic premium ZEROED until LSC commits — base pre-money is now FINANCIAL-ONLY. Restore attribution (row 41-43) when signed.
B37: 5-Year LSC Hardware Margin (link) | C37: =Revenue!C59 | H37: From Revenue tab: locks × LSC margin
B38: 5-Year Accelerant Margin (link) | C38: =Revenue!C60 | H38: Additional locks LSC sells due to Zezamii uplift
B39: 5-Year Panel Margin (link) | C39: =SUM(IF('2. Dashboard'!$B$5="S",'4. Product Forecast'!C31:G31,IF('2. Dashboard'!$B$5="M",'4. Product Forecast'!C63:G63,'4. Product Forecast'!C95:G95)))*'3. Assumptions'!$B$63 | H39: Panels sold via ACaaS — only exist with ProductCo
B40: Attribution to ProductCo partnership
B41: % of hardware margin attributable | C41: 0 | D41: 0 | E41: 0 | H41: ZEROED until LSC commits. When LSC signs, restore: HW=0.5 / accelerant=1.0 / panel=1.0
B42: % of accelerant margin attributable | C42: 0 | D42: 0 | E42: 0 | H42: Accelerant by definition only exists with PCo
B43: % of panel margin attributable | C43: 0 | D43: 0 | E43: 0 | H43: Panels only sold via ACaaS / PCo channel
B44: Total LSC Capture from Partnership (5-yr) | C44: =(C37*C41)+(C38*C42)+(C39*C43)
B45: LSC hurdle rate (lower than VC) | C45: 0.12 | H45: LSC is established distributor — lower cost of capital
B46: NPV of LSC capture (5-yr annuity approx) | C46: =C44/((1+C45)^2.5) | H46: Treated as 5-year level cash flow; conservative approximation
B47: LSC's share of synergy in deal price | C47: LSC keeps | D47: Split 50/50 | E47: PCo keeps most | H47: How much of the LSC-specific value flows into the price LSC pays
B48: LSC retains (paid in price = remainder) | C48: 0.75 | D48: 0.5 | E48: 0.25
B49: Strategic premium paid by LSC ($) | C49: =C46*(1-C48) | D49: =C46*(1-D48) | E49: =C46*(1-E48)
B51: VALUATION RANGE — Financial + Strategic Premium
C52: Conservative | D52: Base | E52: Aggressive
B53: Financial Pre-Money (from row 33) | C53: =C33 | D53: =D33 | E53: =E33
B54: Strategic Premium (from row 49) | C54: =C49 | D54: =D49 | E54: =E49
B55: PRE-MONEY (Financial + Strategic) | C55: =C53+C54 | D55: =D53+D54 | E55: =E53+E54
B57: Implied multiples (check)
B58: vs Y0 ARR | C58: =C55/$C$18 | D58: =D55/$C$18 | E58: =E55/$C$18
B59: vs Y5 ARR | C59: =C55/$C$19 | D59: =D55/$C$19 | E59: =E55/$C$19
B61: COMPARISON TO CURRENT HARDCODED PRE-MONEY
B62: Currently SELECTED Pre-Money (LSC Investment!C19) | C62: ='8. LSC Investment'!C19
B63: Comp-based mid range (Base case) | C63: =D55
B64: Gap (Base − Selected) | C64: =D55-C62
B65: Selected as % of Base | C65: =C62/D55 | H65: If <100%, hardcoded valuation is BELOW market
B67: SENSITIVITY — Pre-Money (Financial only) vs Multiple × Discount Rate
B68: Holds: Y5 ARR (link), ANZ discount 25%, 5-yr horizon
B70: Discount \ Multiple | D70: 3 | E70: 4 | F70: 5 | G70: 6 | H70: 8
C71: 0.2 | D71: =$C$19*D$70*(1-$D$13)/(1+$C71)^5 | E71: =$C$19*E$70*(1-$D$13)/(1+$C71)^5 | F71: =$C$19*F$70*(1-$D$13)/(1+$C71)^5 | G71: =$C$19*G$70*(1-$D$13)/(1+$C71)^5 | H71: =$C$19*H$70*(1-$D$13)/(1+$C71)^5
C72: 0.25 | D72: =$C$19*D$70*(1-$D$13)/(1+$C72)^5 | E72: =$C$19*E$70*(1-$D$13)/(1+$C72)^5 | F72: =$C$19*F$70*(1-$D$13)/(1+$C72)^5 | G72: =$C$19*G$70*(1-$D$13)/(1+$C72)^5 | H72: =$C$19*H$70*(1-$D$13)/(1+$C72)^5
C73: 0.3 | D73: =$C$19*D$70*(1-$D$13)/(1+$C73)^5 | E73: =$C$19*E$70*(1-$D$13)/(1+$C73)^5 | F73: =$C$19*F$70*(1-$D$13)/(1+$C73)^5 | G73: =$C$19*G$70*(1-$D$13)/(1+$C73)^5 | H73: =$C$19*H$70*(1-$D$13)/(1+$C73)^5
C74: 0.35 | D74: =$C$19*D$70*(1-$D$13)/(1+$C74)^5 | E74: =$C$19*E$70*(1-$D$13)/(1+$C74)^5 | F74: =$C$19*F$70*(1-$D$13)/(1+$C74)^5 | G74: =$C$19*G$70*(1-$D$13)/(1+$C74)^5 | H74: =$C$19*H$70*(1-$D$13)/(1+$C74)^5
C75: 0.4 | D75: =$C$19*D$70*(1-$D$13)/(1+$C75)^5 | E75: =$C$19*E$70*(1-$D$13)/(1+$C75)^5 | F75: =$C$19*F$70*(1-$D$13)/(1+$C75)^5 | G75: =$C$19*G$70*(1-$D$13)/(1+$C75)^5 | H75: =$C$19*H$70*(1-$D$13)/(1+$C75)^5
B77: Highlighted = Base assumptions (5x ARR multiple, 30% discount). Strategic premium excluded.
B79: SOURCES & METHODOLOGY
B80: SaaS Valuation Multiples 2026 — Aventis Advisors (https://aventis-advisors.com/saas-valuation-multiples/)
B81: SaaS Valuation Multiples Australia 2026 — Digital Asset Brokers (https://digitalassetbrokers.com.au/saas-valuation-multiples-australia-2026)
B82: PropTech Investment Trends 2026 — Qubit Capital, Software Equity Group, Objective IBV
B83: Strategic vs Financial Buyers — L40°, FE International (2026)
B85: METHODOLOGY:
B86: 1. Forward-Multiple Approach: Y5 ARR (from Cloud Model P&L) × industry multiple, less ANZ discount, discounted to PV at early-stage rate. Standard for SaaS.
B87: 2. Strategic Premium: NPV of LSC-specific value capture (hardware margin × attribution + accelerant + panels), portion passed to PCo per negotiation.
B88: 3. Three cases: Conservative (low multiple + LSC keeps most synergy), Base (mid + 50/50 split), Aggressive (high + PCo keeps most synergy).
B89: 4. Output is a range, not a point. Negotiation range, not a fair value finding.
B92: ACaaS / CLOUD ACCESS CONTROL — DIRECT COMP TRANSACTIONS
B93: Company | C93: Year | D93: Revenue/ARR | E93: Valuation | F93: Multiple | H93: Notes
B94: Verkada | C94: 2025 | D94: 1000000000 | E94: 5800000000 | F94: 5.8 | H94: CapitalG round; AI-driven security; rapid growth ($357M rev 2024 → $1B ARR by Dec 2025)
B95: Brivo | C95: 2021 | D95: 73400000 | E95: 808000000 | F95: 11 | H95: SPAC merger w/ Crown PropTech; smart building ACaaS; closest comp by stage
B96: Openpath | C96: 2021 | D96: 30000000 | E96: 333500000 | F96: 11.1 | H96: Motorola acquisition ($297M-$370M with earn-outs); STRATEGIC ACQUIRER — most relevant precedent for LSC/PCo
B97: Latch | C97: 2021 | E97: 1560000000 | H97: SPAC IPO via Tishman Speyer; smart locks + property mgmt
B98: SwiftConnect | C98: 2024 | H98: Series B $37M (Nov 2024); acquired by Dormakaba Feb 2026 (strategic exit)
B99: Kisi | C99: 2024 | D99: 4000000 | H99: Bootstrapped, declining revenue ($6.7M 2021 → $4M 2024); downside comp
B101: MARKET CONTEXT
B102: ACaaS market 2024: ~$1.34B; forecast $3.06B by 2029 (17.9% CAGR per MarketsandMarkets) or $10.3B by 2032 (22.6% CAGR per SNS Insider)
B103: Cloud security & IAM among top VC categories in 2025-26; SaaS Series A median ~$12M in 2025
B104: ASSA ABLOY acquired 3millID & Third Millennium Systems (Jan 2025) — consolidation continues
B105: Dormakaba acquired SwiftConnect (Feb 2026) — another hardware-incumbent absorbing cloud ACaaS, exact LSC playbook
B106: Strategic acquirers (Motorola, ASSA ABLOY, Dormakaba, Allegion) consistently pay premium multiples for cloud-native ACaaS to defend hardware franchise
B108: IMPLICATIONS FOR PRODUCTCO VALUATION
B109: 1. Direct ACaaS comps trade at 10-12x revenue (Brivo SPAC, Openpath strategic). PropTech vertical bucket (4-8x) UNDERSTATES the right multiple for ACaaS specifically.
B110: 2. The Openpath/Motorola deal is the closest available precedent: industrial/hardware incumbent buying cloud-native ACaaS startup. LSC -> ProductCo is the same archetype.
B111: 3. SwiftConnect/Dormakaba (Feb 2026) confirms this pattern is current and active in Australia/global market.
B112: 4. RECOMMENDATION: Update the multiple range in row 10 (PropTech vertical) upward toward 6-10x to reflect ACaaS-specific data — see updated values below.
B115: TIERED VALUATION — Product-mix specific multiples (vs blended above)
... B118: Multiples by product line
C119: Conservative | D119: Base | E119: Aggressive | G119: Source / Logic
B120: Standard SaaS ARR (× multiple) | C120: 8 | D120: 10 | E120: 12 | G120: Premium SaaS comps: Verkada (~6x but mega-scale), Digital Asset Brokers AU mid-tier (8-10x)
B121: ACaaS Recurring (× multiple) | C121: 5 | D121: 6 | E121: 7 | G121: Hardware-attached SaaS: Brivo 11x at scale, Openpath ~10x strategic — discount for early-stage execution risk
B122: Hardware Revenue (× multiple) | C122: 1 | D122: 1.5 | E122: 2 | G122: Commodity hardware distribution; included for completeness, not premium
...

Sheet 8. LSC Investment
B2: LSC INVESTMENT INTO PRODUCTCO — STRUCTURE
B3: Yellow = inputs. Green = links to other sheets. Black = formulas.
B5: LSC VALUATION INPUTS
B6: Annual Revenue | C6: 50000000 | G6: ESTIMATE — confirm with David
B7: EBITDA | C7: 7500000 | G7: ESTIMATE — confirm with David
B8: EBITDA Margin | C8: =C7/C6 | G8: Calculated
B9: Industry Multiple | C9: 8 | G9: Distribution sector: 6-10x EBITDA
B10: Enterprise Value | C10: =C7*C9 | G10: EBITDA × Multiple
B11: Net Debt | C11: 5000000 | G11: ESTIMATE — confirm with David
B12: LSC Equity Value | C12: =C10-C11 | G12: EV − Net Debt
B14: PRODUCTCO PRE-MONEY (default = comp-based, override available)
B15: Comp-based Pre-Money — Base case (Valuation!D55) | C15: ='7. Valuation'!D55 | G15: Recommended — see Valuation sheet for derivation
B16: Comp-based — Conservative | C16: ='7. Valuation'!C55 | G16: Low end of defensible range
B17: Comp-based — Aggressive | C17: ='7. Valuation'!E55 | G17: High end of defensible range
B18: Override Pre-Money (set non-zero to use) | C18: 0 | G18: Use for negotiating-position scenarios (e.g., LSC anchoring to $3.66M)
B19: SELECTED PRE-MONEY (drives scenarios below) | C19: =IF(C18>0,C18,C15) | G19: Override if set, else Base case
B21: Year 0 ARR (link) | C21: ='3. Assumptions'!B41
B22: Year 5 SaaS ARR (link) | C22: ='5. P&L'!G7
B23: Implied multiple — Selected vs Y0 ARR | C23: =C19/C21
B24: Implied multiple — Selected vs Y5 ARR | C24: =C19/C22
B25: For reference: $5M LSC anchor | C25: 5000000
B26: Selected as % of $3.66M anchor | C26: =C19/C25
B27: EXIT ASSUMPTIONS
B28: Holding Period (years) | C28: 5
B29: LSC Annual Growth (equity value) | C29: 0.1
B30: LSC Equity Value at Exit | C30: =C12*(1+C29)^C28
B31: ProductCo Exit Value (Year N, from Valuation Base) | C31: ='7. Valuation'!D28 | G31: Base case Y5 exit (gross, pre-discount): Y5 ARR × 6x
B32: Override ProductCo Exit (optional) | C32: 0 | G32: Enter non-zero to override the derived value
B33: EFFECTIVE ProductCo Exit Value | C33: =IF(C32>0,C32,C31)
B34: Future Dilution (Series A) | C34: 0.2
B36: INVESTMENT SCENARIOS
B37: Scenario | C37: A: All Cash | D37: B: Blended | E37: C: Equity Heavy | F37: D: Custom
B38: Cash from LSC | C38: 2000000 | D38: 1500000 | E38: 750000 | F38: 1000000
B39: LSC Equity contributed | C39: 0 | D39: 500000 | E39: 1250000 | F39: 1000000
B40: Total Investment | C40: =C38+C39 | D40: =D38+D39 | E40: =E38+E39 | F40: =F38+F39
B42: ProductCo Pre-Money (link) | C42: =$C$19 | D42: =$C$19 | E42: =$C$19 | F42: =$C$19
B43: Post-Money | C43: =C42+C40 | D43: =D42+D40 | E43: =E42+E40 | F43: =F42+F40
B44: LSC % of ProductCo (pre-dilution) | C44: =C40/C43 | D44: =D40/D43 | E44: =E40/E43 | F44: =F40/F43
B45: LSC % of ProductCo (post-dilution) | C45: =C44*(1-$C$34) | D45: =D44*(1-$C$34) | E45: =E44*(1-$C$34) | F45: =F44*(1-$C$34)
B47: ProductCo's % of LSC | C47: =C39/$C$12 | D47: =D39/$C$12 | E47: =E39/$C$12 | F47: =F39/$C$12
B49: RUNWAY (Year 1 burn from selected Team Model)
B50: Year 1 Total Opex (link) | C50: ='Team Summary'!B22 | D50: ='Team Summary'!B22 | E50: ='Team Summary'!B22 | F50: ='Team Summary'!B22
B51: Monthly Burn | C51: =C50/12 | D51: =D50/12 | E51: =E50/12 | F51: =F50/12
B52: Cash Available | C52: =C38 | D52: =D38 | E52: =E38 | F52: =F38
B53: Runway (months) | C53: =C52/C51 | D53: =D52/D51 | E53: =E52/E51 | F53: =F52/F51
B54: Runway (years) | C54: =C53/12 | D54: =D53/12 | E54: =E53/12 | F54: =F53/12
B56: SELECTED SCENARIO (drives Cash Flow!C8)
B57: Dashboard selection | C57: ='2. Dashboard'!B8
B58: Selected Cash | C58: =IF($C$57="A",C38,IF($C$57="B",D38,IF($C$57="C",E38,F38)))
B59: Selected LSC Equity | C59: =IF($C$57="A",C39,IF($C$57="B",D39,IF($C$57="C",E39,F39)))
B60: Selected Runway (months) | C60: =IF($C$57="A",C53,IF($C$57="B",D53,IF($C$57="C",E53,F53)))

Sheet 9. LSC Returns
B2: LSC INVESTMENT — RETURNS ANALYSIS
B4: Scenario | C4: A: All Cash | D4: B: Blended | E4: C: Equity Heavy | F4: D: Custom
B6: VALUES AT EXIT (Year N)
B7: LSC stake in ProductCo (post-dilution) | C7: ='8. LSC Investment'!C45 | D7: ='8. LSC Investment'!D45 | E7: ='8. LSC Investment'!E45 | F7: ='8. LSC Investment'!F45
B8: ProductCo Exit Value | C8: ='8. LSC Investment'!$C$33 | D8: ='8. LSC Investment'!$C$33 | E8: ='8. LSC Investment'!$C$33 | F8: ='8. LSC Investment'!$C$33
B9: LSC stake value at exit | C9: =C7*C8 | D9: =D7*D8 | E9: =E7*E8 | F9: =F7*F8
B11: ProductCo's % of LSC | C11: ='8. LSC Investment'!C47 | D11: ='8. LSC Investment'!D47 | E11: ='8. LSC Investment'!E47 | F11: ='8. LSC Investment'!F47
B12: LSC Equity Value at Exit | C12: ='8. LSC Investment'!$C$30 | D12: ='8. LSC Investment'!$C$30 | E12: ='8. LSC Investment'!$C$30 | F12: ='8. LSC Investment'!$C$30
B13: ProductCo's stake in LSC at exit | C13: =C11*C12 | D13: =D11*D12 | E13: =E11*E12 | F13: =F11*F12
B15: LSC RETURNS (on ProductCo investment)
B16: LSC Total Outlay | C16: ='8. LSC Investment'!C40 | D16: ='8. LSC Investment'!D40 | E16: ='8. LSC Investment'!E40 | F16: ='8. LSC Investment'!F40
B17: LSC Stake Value at Exit | C17: =C9 | D17: =D9 | E17: =E9 | F17: =F9
B18: MOIC | C18: =IFERROR(C17/C16,0) | D18: =IFERROR(D17/D16,0) | E18: =IFERROR(E17/E16,0) | F18: =IFERROR(F17/F16,0)
B19: IRR | C19: =IFERROR((C17/C16)^(1/'8. LSC Investment'!$C$28)-1,0) | D19: =IFERROR((D17/D16)^(1/'8. LSC Investment'!$C$28)-1,0) | E19: =IFERROR((E17/E16)^(1/'8. LSC Investment'!$C$28)-1,0) | F19: =IFERROR((F17/F16)^(1/'8. LSC Investment'!$C$28)-1,0)
B21: PRODUCTCO RETURNS (on LSC equity received)
B22: LSC Equity received (today) | C22: ='8. LSC Investment'!C39 | D22: ='8. LSC Investment'!D39 | E22: ='8. LSC Investment'!E39 | F22: ='8. LSC Investment'!F39
B23: Value at Exit | C23: =C13 | D23: =D13 | E23: =E13 | F23: =F13
B24: MOIC | C24: =IFERROR(C23/C22,"N/A") | D24: =IFERROR(D23/D22,"N/A") | E24: =IFERROR(E23/E22,"N/A") | F24: =IFERROR(F23/F22,"N/A")
B25: IRR | C25: =IFERROR((C23/C22)^(1/'8. LSC Investment'!$C$28)-1,"N/A") | D25: =IFERROR((D23/D22)^(1/'8. LSC Investment'!$C$28)-1,"N/A") | E25: =IFERROR((E23/E22)^(1/'8. LSC Investment'!$C$28)-1,"N/A") | F25: =IFERROR((F23/F22)^(1/'8. LSC Investment'!$C$28)-1,"N/A")
B27: Note: LSC IRR on ProductCo stake is identical across scenarios because total investment ($2M) is constant.
B28: ProductCo IRR on LSC equity = LSC growth rate (passive holding).

Sheet 10. LSC Sensitivity
B2: LSC INVESTMENT — SENSITIVITY
B4: LSC EQUITY VALUE — Sensitivity to EBITDA × Multiple
B5: Net Debt held constant at: | C5: ='8. LSC Investment'!C11
B7: EBITDA \ Multiple | D7: 6 | E7: 7 | F7: 8 | G7: 9 | H7: 10
C8: 5000000 | D8: =$C8*D$7-$C$5 | E8: =$C8*E$7-$C$5 | F8: =$C8*F$7-$C$5 | G8: =$C8*G$7-$C$5 | H8: =$C8*H$7-$C$5
C9: 6500000 | D9: =$C9*D$7-$C$5 | E9: =$C9*E$7-$C$5 | F9: =$C9*F$7-$C$5 | G9: =$C9*G$7-$C$5 | H9: =$C9*H$7-$C$5
C10: 7500000 | D10: =$C10*D$7-$C$5 | E10: =$C10*E$7-$C$5 | F10: =$C10*F$7-$C$5 | G10: =$C10*G$7-$C$5 | H10: =$C10*H$7-$C$5
C11: 9000000 | D11: =$C11*D$7-$C$5 | E11: =$C11*E$7-$C$5 | F11: =$C11*F$7-$C$5 | G11: =$C11*G$7-$C$5 | H11: =$C11*H$7-$C$5
C12: 11000000 | D12: =$C12*D$7-$C$5 | E12: =$C12*E$7-$C$5 | F12: =$C12*F$7-$C$5 | G12: =$C12*G$7-$C$5 | H12: =$C12*H$7-$C$5
B13: Highlighted = base case (7.5M EBITDA × 8x)
B15: LSC IRR ON PRODUCTCO — Exit Value × Holding Period
B16: Scenario A ($2M cash), post-dilution stake: | C16: ='8. LSC Investment'!C45
B18: Exit Value \ Years | D18: 3 | E18: 4 | F18: 5 | G18: 7 | H18: 10
C19: 10000000 | D19: =IFERROR(($C$16*$C19/'8. LSC Investment'!$C$40)^(1/D$18)-1,0) | E19: =IFERROR(($C$16*$C19/'8. LSC Investment'!$C$40)^(1/E$18)-1,0) | F19: =IFERROR(($C$16*$C19/'8. LSC Investment'!$C$40)^(1/F$18)-1,0) | G19: =IFERROR(($C$16*$C19/'8. LSC Investment'!$C$40)^(1/G$18)-1,0) | H19: =IFERROR(($C$16*$C19/'8. LSC Investment'!$C$40)^(1/H$18)-1,0)
C20: 20000000 | D20: =IFERROR(($C$16*$C20/'8. LSC Investment'!$C$40)^(1/D$18)-1,0) | E20: =IFERROR(($C$16*$C20/'8. LSC Investment'!$C$40)^(1/E$18)-1,0) | F20: =IFERROR(($C$16*$C20/'8. LSC Investment'!$C$40)^(1/F$18)-1,0) | G20: =IFERROR(($C$16*$C20/'8. LSC Investment'!$C$40)^(1/G$18)-1,0) | H20: =IFERROR(($C$16*$C20/'8. LSC Investment'!$C$40)^(1/H$18)-1,0)
C21: 30000000 | D21: =IFERROR(($C$16*$C21/'8. LSC Investment'!$C$40)^(1/D$18)-1,0) | E21: =IFERROR(($C$16*$C21/'8. LSC Investment'!$C$40)^(1/E$18)-1,0) | F21: =IFERROR(($C$16*$C21/'8. LSC Investment'!$C$40)^(1/F$18)-1,0) | G21: =IFERROR(($C$16*$C21/'8. LSC Investment'!$C$40)^(1/G$18)-1,0) | H21: =IFERROR(($C$16*$C21/'8. LSC Investment'!$C$40)^(1/H$18)-1,0)
C22: 50000000 | D22: =IFERROR(($C$16*$C22/'8. LSC Investment'!$C$40)^(1/D$18)-1,0) | E22: =IFERROR(($C$16*$C22/'8. LSC Investment'!$C$40)^(1/E$18)-1,0) | F22: =IFERROR(($C$16*$C22/'8. LSC Investment'!$C$40)^(1/F$18)-1,0) | G22: =IFERROR(($C$16*$C22/'8. LSC Investment'!$C$40)^(1/G$18)-1,0) | H22: =IFERROR(($C$16*$C22/'8. LSC Investment'!$C$40)^(1/H$18)-1,0)
C23: 100000000 | D23: =IFERROR(($C$16*$C23/'8. LSC Investment'!$C$40)^(1/D$18)-1,0) | E23: =IFERROR(($C$16*$C23/'8. LSC Investment'!$C$40)^(1/E$18)-1,0) | F23: =IFERROR(($C$16*$C23/'8. LSC Investment'!$C$40)^(1/F$18)-1,0) | G23: =IFERROR(($C$16*$C23/'8. LSC Investment'!$C$40)^(1/G$18)-1,0) | H23: =IFERROR(($C$16*$C23/'8. LSC Investment'!$C$40)^(1/H$18)-1,0)
B24: Highlighted = base case ($30M exit, 5 years)
B26: PRODUCTCO EXIT — sensitivity to Y5 ARR multiple × discount rate
B27: Year 5 SaaS ARR: | C27: ='5. P&L'!G7
B29: ARR Mult \ Disc Rate | D29: 0.2 | E29: 0.25 | F29: 0.3 | G29: 0.35 | H29: 0.4
C30: 3 | D30: =$C$27*$C30/(1+D$29)^5 | E30: =$C$27*$C30/(1+E$29)^5 | F30: =$C$27*$C30/(1+F$29)^5 | G30: =$C$27*$C30/(1+G$29)^5 | H30: =$C$27*$C30/(1+H$29)^5
C31: 4 | D31: =$C$27*$C31/(1+D$29)^5 | E31: =$C$27*$C31/(1+E$29)^5 | F31: =$C$27*$C31/(1+F$29)^5 | G31: =$C$27*$C31/(1+G$29)^5 | H31: =$C$27*$C31/(1+H$29)^5
C32: 5 | D32: =$C$27*$C32/(1+D$29)^5 | E32: =$C$27*$C32/(1+E$29)^5 | F32: =$C$27*$C32/(1+F$29)^5 | G32: =$C$27*$C32/(1+G$29)^5 | H32: =$C$27*$C32/(1+H$29)^5
C33: 6 | D33: =$C$27*$C33/(1+D$29)^5 | E33: =$C$27*$C33/(1+E$29)^5 | F33: =$C$27*$C33/(1+F$29)^5 | G33: =$C$27*$C33/(1+G$29)^5 | H33: =$C$27*$C33/(1+H$29)^5
C34: 8 | D34: =$C$27*$C34/(1+D$29)^5 | E34: =$C$27*$C34/(1+E$29)^5 | F34: =$C$27*$C34/(1+F$29)^5 | G34: =$C$27*$C34/(1+G$29)^5 | H34: =$C$27*$C34/(1+H$29)^5
B35: Highlighted = base case (5x ARR, 30% discount). Compare to $3.66M hardcoded pre-money.

Sheet Revenue
A1: REVENUE MODEL — Zezamii Cloud
A3: Metric | B3: Year 0 | C3: Year 1 | D3: Year 2 | E3: Year 3 | F3: Year 4 | G3: Year 5 | H3: Notes
A4: SITE GROWTH
A5: New Sites (this year) | B5: 0 | C5: =IF('2. Dashboard'!$B$5="S",'3. Assumptions'!$B$28,IF('2. Dashboard'!$B$5="M",'3. Assumptions'!$B$29,'3. Assumptions'!$B$30)) | D5: =ROUND(C5*IF('2. Dashboard'!$B$5="S",'3. Assumptions'!$B$31,IF('2. Dashboard'!$B$5="M",'3. Assumptions'!$B$32,'3. Assumptions'!$B$33)),0) | E5: =ROUND(D5*IF('2. Dashboard'!$B$5="S",'3. Assumptions'!$B$31,IF('2. Dashboard'!$B$5="M",'3. Assumptions'!$B$32,'3. Assumptions'!$B$33)),0) | F5: =ROUND(E5*IF('2. Dashboard'!$B$5="S",'3. Assumptions'!$B$31,IF('2. Dashboard'!$B$5="M",'3. Assumptions'!$B$32,'3. Assumptions'!$B$33)),0) | G5: =ROUND(F5*IF('2. Dashboard'!$B$5="S",'3. Assumptions'!$B$31,IF('2. Dashboard'!$B$5="M",'3. Assumptions'!$B$32,'3. Assumptions'!$B$33)),0) | H5: Based on Dashboard scenario
A6: Cumulative Sites | B6: ='3. Assumptions'!B40 | C6: =B6+C5-ROUND(B6*'3. Assumptions'!$B$35,0) | D6: =C6+D5-ROUND(C6*'3. Assumptions'!$B$35,0) | E6: =D6+E5-ROUND(D6*'3. Assumptions'!$B$35,0) | F6: =E6+F5-ROUND(E6*'3. Assumptions'!$B$35,0) | G6: =F6+G5-ROUND(F6*'3. Assumptions'!$B$35,0) | H6: Incl. churn
A7: Churned Sites | C7: =ROUND(B6*'3. Assumptions'!$B$35,0) | D7: =ROUND(C6*'3. Assumptions'!$B$35,0) | E7: =ROUND(D6*'3. Assumptions'!$B$35,0) | F7: =ROUND(E6*'3. Assumptions'!$B$35,0) | G7: =ROUND(F6*'3. Assumptions'!$B$35,0)
A9: PARTNER MIX
A10: Partner Level | C10: n/a (single margin)
A11: Partner Margin % | C11: ='3. Assumptions'!$B$21
A12: Net to Zezamii % | C12: =1-C11
A14: SaaS REVENUE
A15: Blended ARR per Site (retail) | C15: ='4. Product Forecast'!$C$103 | D15: =C15*(1+'3. Assumptions'!$B$37) | E15: =D15*(1+'3. Assumptions'!$B$37) | F15: =E15*(1+'3. Assumptions'!$B$37) | G15: =F15*(1+'3. Assumptions'!$B$37)
A16: Blended ARR per Site (net) | C16: =C15*$C$12 | D16: =D15*$C$12 | E16: =E15*$C$12 | F16: =F15*$C$12 | G16: =G15*$C$12
A18: Standard Cloud ARR (new sites) | C18: =IF(1>='3. Assumptions'!$B$58, (C5-C66)*C16, C5*C16) | D18: =IF(2>='3. Assumptions'!$B$58, (D5-D66)*D16, D5*D16) | E18: =IF(3>='3. Assumptions'!$B$58, (E5-E66)*E16, E5*E16) | F18: =IF(4>='3. Assumptions'!$B$58, (F5-F66)*F16, F5*F16) | G18: =IF(5>='3. Assumptions'!$B$58, (G5-G66)*G16, G5*G16)
A19: Existing Site ARR (retained) | B19: ='3. Assumptions'!B41 | C19: =B19*(1-'3. Assumptions'!$B$35)*(1+'3. Assumptions'!$B$37) | D19: =(C19+C18)*(1-'3. Assumptions'!$B$35)*(1+'3. Assumptions'!$B$37) | E19: =(D19+D18)*(1-'3. Assumptions'!$B$35)*(1+'3. Assumptions'!$B$37) | F19: =(E19+E18)*(1-'3. Assumptions'!$B$35)*(1+'3. Assumptions'!$B$37) | G19: =(F19+F18)*(1-'3. Assumptions'!$B$35)*(1+'3. Assumptions'!$B$37)
A20: Churned ARR | C20: =B19*'3. Assumptions'!$B$35 | D20: =(C19+C18)*'3. Assumptions'!$B$35 | E20: =(D19+D18)*'3. Assumptions'!$B$35 | F20: =(E19+E18)*'3. Assumptions'!$B$35 | G20: =(F19+F18)*'3. Assumptions'!$B$35
A22: Price Uplift (existing sites) | C22: 0 | D22: =C19*'3. Assumptions'!$B$37 | E22: =D19*'3. Assumptions'!$B$37 | F22: =E19*'3. Assumptions'!$B$37 | G22: =F19*'3. Assumptions'!$B$37
A25: STANDARD CLOUD ARR | B25: =B19 | C25: =IF('2. Dashboard'!$B$5="S",'4. Product Forecast'!C25,IF('2. Dashboard'!$B$5="M",'4. Product Forecast'!C57,'4. Product Forecast'!C89)) + ('3. Assumptions'!$B$41 - '3. Assumptions'!$B$40 * (0.4*'3. Assumptions'!$B$5 + 0.35*'3. Assumptions'!$B$6 + 0.2*'3. Assumptions'!$B$7 + 0.05*'3. Assumptions'!$B$8) * (1-'3. Assumptions'!$B$21)) * (1-'3. Assumptions'!$B$35)^1 * (1+'3. Assumptions'!$B$37)^1 | D25: =IF('2. Dashboard'!$B$5="S",'4. Product Forecast'!D25,IF('2. Dashboard'!$B$5="M",'4. Product Forecast'!D57,'4. Product Forecast'!D89)) + ('3. Assumptions'!$B$41 - '3. Assumptions'!$B$40 * (0.4*'3. Assumptions'!$B$5 + 0.35*'3. Assumptions'!$B$6 + 0.2*'3. Assumptions'!$B$7 + 0.05*'3. Assumptions'!$B$8) * (1-'3. Assumptions'!$B$21)) * (1-'3. Assumptions'!$B$35)^2 * (1+'3. Assumptions'!$B$37)^2 | E25: =IF('2. Dashboard'!$B$5="S",'4. Product Forecast'!E25,IF('2. Dashboard'!$B$5="M",'4. Product Forecast'!E57,'4. Product Forecast'!E89)) + ('3. Assumptions'!$B$41 - '3. Assumptions'!$B$40 * (0.4*'3. Assumptions'!$B$5 + 0.35*'3. Assumptions'!$B$6 + 0.2*'3. Assumptions'!$B$7 + 0.05*'3. Assumptions'!$B$8) * (1-'3. Assumptions'!$B$21)) * (1-'3. Assumptions'!$B$35)^3 * (1+'3. Assumptions'!$B$37)^3 | F25: =IF('2. Dashboard'!$B$5="S",'4. Product Forecast'!F25,IF('2. Dashboard'!$B$5="M",'4. Product Forecast'!F57,'4. Product Forecast'!F89)) + ('3. Assumptions'!$B$41 - '3. Assumptions'!$B$40 * (0.4*'3. Assumptions'!$B$5 + 0.35*'3. Assumptions'!$B$6 + 0.2*'3. Assumptions'!$B$7 + 0.05*'3. Assumptions'!$B$8) * (1-'3. Assumptions'!$B$21)) * (1-'3. Assumptions'!$B$35)^4 * (1+'3. Assumptions'!$B$37)^4 | G25: =IF('2. Dashboard'!$B$5="S",'4. Product Forecast'!G25,IF('2. Dashboard'!$B$5="M",'4. Product Forecast'!G57,'4. Product Forecast'!G89)) + ('3. Assumptions'!$B$41 - '3. Assumptions'!$B$40 * (0.4*'3. Assumptions'!$B$5 + 0.35*'3. Assumptions'!$B$6 + 0.2*'3. Assumptions'!$B$7 + 0.05*'3. Assumptions'!$B$8) * (1-'3. Assumptions'!$B$21)) * (1-'3. Assumptions'!$B$35)^5 * (1+'3. Assumptions'!$B$37)^5
A26: ARR via LSC Channel | C26: =C25*'3. Assumptions'!$B$80 | D26: =D25*'3. Assumptions'!$B$81 | E26: =E25*'3. Assumptions'!$B$82 | F26: =F25*'3. Assumptions'!$B$83 | G26: =G25*'3. Assumptions'!$B$84 | H26: Assumed LSC % of sales
A28: HARDWARE REVENUE
A29: Locks per New Site (blended) | C29: ='4. Product Forecast'!$C$104 | D29: =C29 | E29: =D29 | F29: =E29 | G29: =F29
A30: Hardware Revenue (new sites) | C30: =C5*C29*'3. Assumptions'!$B$18 | D30: =D5*D29*'3. Assumptions'!$B$18 | E30: =E5*E29*'3. Assumptions'!$B$18 | F30: =F5*F29*'3. Assumptions'!$B$18 | G30: =G5*G29*'3. Assumptions'!$B$18
A31: Hardware Margin (pass-through) | C31: =C30*0.15 | D31: =D30*0.15 | E31: =E30*0.15 | F31: =F30*0.15 | G31: =G30*0.15 | H31: Hardware margin = 25% Zezamii / 75% LSC (Assumptions!B22). Prior "15% vs 35%" note was mislabeled.
A33: TOTAL REVENUE | C33: =C25+C30 | D33: =D25+D30 | E33: =E25+E30 | F33: =F25+F30 | G33: =G25+G30
A35: GROWTH SCENARIO SUMMARY
A36: Selected Scenario | C36: ='2. Dashboard'!B5
A37: Year 1 Sites | C37: =C5
A38: Growth Multiplier (selected) | C38: =IF('2. Dashboard'!$B$5="S",'3. Assumptions'!$B$31,IF('2. Dashboard'!$B$5="M",'3. Assumptions'!$B$32,'3. Assumptions'!$B$33))
A39: 5-Year Total New Sites | C39: =SUM(C5:G5)
A41: LSC BASE CONTEXT
A42: LSC B2B Sites (convertible) | C42: ='3. Assumptions'!B50
A43: Year 1-2 New Sites | C43: =C5+D5
A44: % of LSC Base Captured (Y1-2) | C44: =IF(C42>0, C43/C42, 0) | H44: WARNING: >100% means projected sites exceed LSC convertible base — projections may be unrealistic vs LSC actual base
A46: LSC VALUE CREATION
A47: Locks Sold via Zezamii Sites | C47: =IF('2. Dashboard'!$B$5="S",'4. Product Forecast'!C28,IF('2. Dashboard'!$B$5="M",'4. Product Forecast'!C60,'4. Product Forecast'!C92)) | D47: =IF('2. Dashboard'!$B$5="S",'4. Product Forecast'!D28,IF('2. Dashboard'!$B$5="M",'4. Product Forecast'!D60,'4. Product Forecast'!D92)) | E47: =IF('2. Dashboard'!$B$5="S",'4. Product Forecast'!E28,IF('2. Dashboard'!$B$5="M",'4. Product Forecast'!E60,'4. Product Forecast'!E92)) | F47: =IF('2. Dashboard'!$B$5="S",'4. Product Forecast'!F28,IF('2. Dashboard'!$B$5="M",'4. Product Forecast'!F60,'4. Product Forecast'!F92)) | G47: =IF('2. Dashboard'!$B$5="S",'4. Product Forecast'!G28,IF('2. Dashboard'!$B$5="M",'4. Product Forecast'!G60,'4. Product Forecast'!G92)) | H47: New site locks
A48: Accelerant Uplift (additional locks) | C48: =C47*'3. Assumptions'!$B$53 | D48: =D47*'3. Assumptions'!$B$53 | E48: =E47*'3. Assumptions'!$B$53 | F48: =F47*'3. Assumptions'!$B$53 | G48: =G47*'3. Assumptions'!$B$53 | H48: Extra locks due to Zezamii
A49: Total Locks (with Zezamii effect) | C49: =C47+C48 | D49: =D47+D48 | E49: =E47+E48 | F49: =F47+F48 | G49: =G47+G48
A51: LSC Hardware Revenue (locks) | C51: =C49*'3. Assumptions'!$B$54 | D51: =D49*'3. Assumptions'!$B$54 | E51: =E49*'3. Assumptions'!$B$54 | F51: =F49*'3. Assumptions'!$B$54 | G51: =G49*'3. Assumptions'!$B$54
A52: LSC Hardware Margin | C52: =C51*'3. Assumptions'!$B$55 | D52: =D51*'3. Assumptions'!$B$55 | E52: =E51*'3. Assumptions'!$B$55 | F52: =F51*'3. Assumptions'!$B$55 | G52: =G51*'3. Assumptions'!$B$55 | H52: What LSC earns
A54: VALUE FROM ACCELERANT ONLY | C54: =C48*'3. Assumptions'!$B$54*'3. Assumptions'!$B$55 | D54: =D48*'3. Assumptions'!$B$54*'3. Assumptions'!$B$55 | E54: =E48*'3. Assumptions'!$B$54*'3. Assumptions'!$B$55 | F54: =F48*'3. Assumptions'!$B$54*'3. Assumptions'!$B$55 | G54: =G48*'3. Assumptions'!$B$54*'3. Assumptions'!$B$55 | H54: Additional margin from Zezamii uplift
A56: 5-YEAR LSC VALUE SUMMARY
A57: Total Locks Sold | C57: =SUM(C49:G49)
A58: Total LSC Hardware Revenue | C58: =SUM(C51:G51)
A59: Total LSC Hardware Margin | C59: =SUM(C52:G52)
A60: Margin from Accelerant Effect | C60: =SUM(C54:G54)
A62: ACaaS REVENUE (INTEGRATED PANEL)
A63: ACaaS Available? | C63: =IF(1>='3. Assumptions'!$B$58,"Yes","No") | D63: =IF(2>='3. Assumptions'!$B$58,"Yes","No") | E63: =IF(3>='3. Assumptions'!$B$58,"Yes","No") | F63: =IF(4>='3. Assumptions'!$B$58,"Yes","No") | G63: =IF(5>='3. Assumptions'!$B$58,"Yes","No")
A64: ACaaS Ramp Factor | C64: =IF(1<'3. Assumptions'!$B$58,0,IF(1='3. Assumptions'!$B$58,'3. Assumptions'!$B$64,'3. Assumptions'!$B$65)) | D64: =IF(2<'3. Assumptions'!$B$58,0,IF(2='3. Assumptions'!$B$58,'3. Assumptions'!$B$64,'3. Assumptions'!$B$65)) | E64: =IF(3<'3. Assumptions'!$B$58,0,IF(3='3. Assumptions'!$B$58,'3. Assumptions'!$B$64,'3. Assumptions'!$B$65)) | F64: =IF(4<'3. Assumptions'!$B$58,0,IF(4='3. Assumptions'!$B$58,'3. Assumptions'!$B$64,'3. Assumptions'!$B$65)) | G64: =IF(5<'3. Assumptions'!$B$58,0,IF(5='3. Assumptions'!$B$58,'3. Assumptions'!$B$64,'3. Assumptions'!$B$65))
A65: New Sites (total) | C65: =C5 | D65: =D5 | E65: =E5 | F65: =F5 | G65: =G5
A66: ACaaS Sites (new) | C66: =ROUND(C65*'3. Assumptions'!$B$60*C64,0) | D66: =ROUND(D65*'3. Assumptions'!$B$60*D64,0) | E66: =ROUND(E65*'3. Assumptions'!$B$60*E64,0) | F66: =ROUND(F65*'3. Assumptions'!$B$60*F64,0) | G66: =ROUND(G65*'3. Assumptions'!$B$60*G64,0)
A67: Standard Cloud Sites (new) | C67: =C65-C66 | D67: =D65-D66 | E67: =E65-E66 | F67: =F65-F66 | G67: =G65-G66
A69: ACaaS ARR (new sites) | C69: =C66*'3. Assumptions'!$B$59 | D69: =D66*'3. Assumptions'!$B$59 | E69: =E66*'3. Assumptions'!$B$59 | F69: =F66*'3. Assumptions'!$B$59 | G69: =G66*'3. Assumptions'!$B$59
A70: ACaaS ARR (cumulative) | C70: =IF('2. Dashboard'!$B$5="S",'4. Product Forecast'!C24,IF('2. Dashboard'!$B$5="M",'4. Product Forecast'!C56,'4. Product Forecast'!C88)) | D70: =IF('2. Dashboard'!$B$5="S",'4. Product Forecast'!D24,IF('2. Dashboard'!$B$5="M",'4. Product Forecast'!D56,'4. Product Forecast'!D88)) | E70: =IF('2. Dashboard'!$B$5="S",'4. Product Forecast'!E24,IF('2. Dashboard'!$B$5="M",'4. Product Forecast'!E56,'4. Product Forecast'!E88)) | F70: =IF('2. Dashboard'!$B$5="S",'4. Product Forecast'!F24,IF('2. Dashboard'!$B$5="M",'4. Product Forecast'!F56,'4. Product Forecast'!F88)) | G70: =IF('2. Dashboard'!$B$5="S",'4. Product Forecast'!G24,IF('2. Dashboard'!$B$5="M",'4. Product Forecast'!G56,'4. Product Forecast'!G88))
A72: ACaaS Panel Hardware
A73: Panels Sold | C73: =C66*'3. Assumptions'!$B$61 | D73: =D66*'3. Assumptions'!$B$61 | E73: =E66*'3. Assumptions'!$B$61 | F73: =F66*'3. Assumptions'!$B$61 | G73: =G66*'3. Assumptions'!$B$61
A74: Panel Revenue | C74: =C73*'3. Assumptions'!$B$62 | D74: =D73*'3. Assumptions'!$B$62 | E74: =E73*'3. Assumptions'!$B$62 | F74: =F73*'3. Assumptions'!$B$62 | G74: =G73*'3. Assumptions'!$B$62
A75: LSC Panel Margin | C75: =C74*'3. Assumptions'!$B$63 | D75: =D74*'3. Assumptions'!$B$63 | E75: =E74*'3. Assumptions'!$B$63 | F75: =F74*'3. Assumptions'!$B$63 | G75: =G74*'3. Assumptions'!$B$63
A77: COMBINED REVENUE SUMMARY
A78: Standard Cloud ARR | C78: =C25 | D78: =D25 | E78: =E25 | F78: =F25 | G78: =G25
A79: ACaaS ARR | C79: =C70 | D79: =D70 | E79: =E70 | F79: =F70 | G79: =G70
A80: TOTAL PLATFORM ARR | C80: =C78+C79 | D80: =D78+D79 | E80: =E78+E79 | F80: =F78+F79 | G80: =G78+G79
A82: Lock Hardware Revenue | C82: =IF('2. Dashboard'!$B$5="S",'4. Product Forecast'!C29,IF('2. Dashboard'!$B$5="M",'4. Product Forecast'!C61,'4. Product Forecast'!C93)) | D82: =IF('2. Dashboard'!$B$5="S",'4. Product Forecast'!D29,IF('2. Dashboard'!$B$5="M",'4. Product Forecast'!D61,'4. Product Forecast'!D93)) | E82: =IF('2. Dashboard'!$B$5="S",'4. Product Forecast'!E29,IF('2. Dashboard'!$B$5="M",'4. Product Forecast'!E61,'4. Product Forecast'!E93)) | F82: =IF('2. Dashboard'!$B$5="S",'4. Product Forecast'!F29,IF('2. Dashboard'!$B$5="M",'4. Product Forecast'!F61,'4. Product Forecast'!F93)) | G82: =IF('2. Dashboard'!$B$5="S",'4. Product Forecast'!G29,IF('2. Dashboard'!$B$5="M",'4. Product Forecast'!G61,'4. Product Forecast'!G93))
A83: Panel Hardware Revenue | C83: =IF('2. Dashboard'!$B$5="S",'4. Product Forecast'!C31,IF('2. Dashboard'!$B$5="M",'4. Product Forecast'!C63,'4. Product Forecast'!C95)) | D83: =IF('2. Dashboard'!$B$5="S",'4. Product Forecast'!D31,IF('2. Dashboard'!$B$5="M",'4. Product Forecast'!D63,'4. Product Forecast'!D95)) | E83: =IF('2. Dashboard'!$B$5="S",'4. Product Forecast'!E31,IF('2. Dashboard'!$B$5="M",'4. Product Forecast'!E63,'4. Product Forecast'!E95)) | F83: =IF('2. Dashboard'!$B$5="S",'4. Product Forecast'!F31,IF('2. Dashboard'!$B$5="M",'4. Product Forecast'!F63,'4. Product Forecast'!F95)) | G83: =IF('2. Dashboard'!$B$5="S",'4. Product Forecast'!G31,IF('2. Dashboard'!$B$5="M",'4. Product Forecast'!G63,'4. Product Forecast'!G95))
A84: TOTAL HARDWARE REVENUE | C84: =C82+C83 | D84: =D82+D83 | E84: =E82+E83 | F84: =F82+F83 | G84: =G82+G83
A86: TOTAL REVENUE (SaaS + Hardware) | C86: =C80+C84 | D86: =D80+D84 | E86: =E80+E84 | F86: =F80+F84 | G86: =G80+G84

Sheet Team - S
A1: TEAM COSTS — Product Model (Lean)
A2: Glenn + Kishan + Duvan at 100% allocation
A4: Role | B4: Person | C4: Full Cost | D4: Allocation | E4: Year 1 | F4: Year 2 | G4: Year 3 | H4: Year 4 | I4: Year 5
A5: Director | B5: Glenn | C5: 100000 | D5: 1 | E5: =C5*D5 | F5: =E5*(1+'3. Assumptions'!$B$36) | G5: =F5*(1+'3. Assumptions'!$B$36) | H5: =G5*(1+'3. Assumptions'!$B$36) | I5: =H5*(1+'3. Assumptions'!$B$36)
A6: Head of Engineering | B6: Kishan | C6: 170000 | D6: 1 | E6: =C6*D6 | F6: =E6*(1+'3. Assumptions'!$B$36) | G6: =F6*(1+'3. Assumptions'!$B$36) | H6: =G6*(1+'3. Assumptions'!$B$36) | I6: =H6*(1+'3. Assumptions'!$B$36)
A7: Fullstack Dev | B7: Duvan | C7: 110000 | D7: 1 | E7: =C7*D7 | F7: =E7*(1+'3. Assumptions'!$B$36) | G7: =F7*(1+'3. Assumptions'!$B$36) | H7: =G7*(1+'3. Assumptions'!$B$36) | I7: =H7*(1+'3. Assumptions'!$B$36)
A9: TOTAL TEAM COST | E9: =SUM(E5:E7) | F9: =SUM(F5:F7) | G9: =SUM(G5:G7) | H9: =SUM(H5:H7) | I9: =SUM(I5:I7)
A11: OTHER OPERATING COSTS
A12: Rent & Facilities | B12: 52000 | E12: =B12 | F12: =E12*(1+'3. Assumptions'!$B$37) | G12: =F12*(1+'3. Assumptions'!$B$37) | H12: =G12*(1+'3. Assumptions'!$B$37) | I12: =H12*(1+'3. Assumptions'!$B$37)
A13: Software & Subscriptions | B13: 40000 | E13: =B13 | F13: =E13*(1+'3. Assumptions'!$B$37) | G13: =F13*(1+'3. Assumptions'!$B$37) | H13: =G13*(1+'3. Assumptions'!$B$37) | I13: =H13*(1+'3. Assumptions'!$B$37)
A14: Insurance | B14: 12000 | E14: =B14 | F14: =E14*(1+'3. Assumptions'!$B$37) | G14: =F14*(1+'3. Assumptions'!$B$37) | H14: =G14*(1+'3. Assumptions'!$B$37) | I14: =H14*(1+'3. Assumptions'!$B$37)
A15: Professional Services | B15: 24000 | E15: =B15 | F15: =E15*(1+'3. Assumptions'!$B$37) | G15: =F15*(1+'3. Assumptions'!$B$37) | H15: =G15*(1+'3. Assumptions'!$B$37) | I15: =H15*(1+'3. Assumptions'!$B$37)
A17: TOTAL OTHER OPEX | E17: =SUM(E12:E15) | F17: =SUM(F12:F15) | G17: =SUM(G12:G15) | H17: =SUM(H12:H15) | I17: =SUM(I12:I15)
A19: TOTAL OPERATING COSTS | B19: 12000 | E19: =E9+E17 | F19: =F9+F17 | G19: =G9+G17 | H19: =H9+H17 | I19: =I9+I17

Sheet Team - M
A1: TEAM COSTS — Zezamii Cloud
A3: Role | B3: Person | C3: Full Cost | D3: Allocation | E3: Year 1 | F3: Year 2 | G3: Year 3 | H3: Year 4 | I3: Year 5
A4: Director | B4: Glenn | C4: 200000 | D4: 0.5 | E4: =C4*D4 | F4: =E4*(1+'3. Assumptions'!$B$36) | G4: =F4*(1+'3. Assumptions'!$B$36) | H4: =G4*(1+'3. Assumptions'!$B$36) | I4: =H4*(1+'3. Assumptions'!$B$36)
A5: Head of Engineering | B5: Kishan | C5: 170000 | D5: 1 | E5: =C5*D5 | F5: =E5*(1+'3. Assumptions'!$B$36) | G5: =F5*(1+'3. Assumptions'!$B$36) | H5: =G5*(1+'3. Assumptions'!$B$36) | I5: =H5*(1+'3. Assumptions'!$B$36)
A6: Fullstack Dev | B6: Duvan | C6: 110000 | D6: 1 | E6: =C6*D6 | F6: =E6*(1+'3. Assumptions'!$B$36) | G6: =F6*(1+'3. Assumptions'!$B$36) | H6: =G6*(1+'3. Assumptions'!$B$36) | I6: =H6*(1+'3. Assumptions'!$B$36)
A7: Co-founder | B7: Warren | C7: 200000 | D7: 0.2 | E7: =C7*D7 | F7: =E7*(1+'3. Assumptions'!$B$36) | G7: =F7*(1+'3. Assumptions'!$B$36) | H7: =G7*(1+'3. Assumptions'!$B$36) | I7: =H7*(1+'3. Assumptions'!$B$36)
A8: Support | B8: Luke | C8: 100000 | D8: 0.5 | E8: =C8*D8 | F8: =E8*(1+'3. Assumptions'!$B$36) | G8: =F8*(1+'3. Assumptions'!$B$36) | H8: =G8*(1+'3. Assumptions'!$B$36) | I8: =H8*(1+'3. Assumptions'!$B$36)
A10: FUTURE HIRES
A11: Sales/BD | B11: TBD | C11: 135000 | D11: 1 | E11: 0 | F11: =IF(Revenue!D25>=350000, C11, 0) | G11: =IF(F11>0, F11*(1+'3. Assumptions'!$B$36), IF(Revenue!E25>=350000, C11, 0)) | H11: =IF(G11>0, G11*(1+'3. Assumptions'!$B$36), IF(Revenue!F25>=350000, C11, 0)) | I11: =IF(H11>0, H11*(1+'3. Assumptions'!$B$36), IF(Revenue!G25>=350000, C11, 0))
C12: Trigger: $350K ARR
A14: TOTAL TEAM COST | E14: =SUM(E4:E8)+E11 | F14: =SUM(F4:F8)+F11 | G14: =SUM(G4:G8)+G11 | H14: =SUM(H4:H8)+H11 | I14: =SUM(I4:I8)+I11
A16: OTHER OPERATING COSTS
A17: Rent & Facilities | B17: 45000 | E17: =B17 | F17: =E17*(1+'3. Assumptions'!$B$37) | G17: =F17*(1+'3. Assumptions'!$B$37) | H17: =G17*(1+'3. Assumptions'!$B$37) | I17: =H17*(1+'3. Assumptions'!$B$37)
A18: Software & Subscriptions | B18: 50000 | E18: =B18 | F18: =E18*(1+'3. Assumptions'!$B$37) | G18: =F18*(1+'3. Assumptions'!$B$37) | H18: =G18*(1+'3. Assumptions'!$B$37) | I18: =H18*(1+'3. Assumptions'!$B$37)
A19: Insurance | B19: 15000 | E19: =B19 | F19: =E19*(1+'3. Assumptions'!$B$37) | G19: =F19*(1+'3. Assumptions'!$B$37) | H19: =G19*(1+'3. Assumptions'!$B$37) | I19: =H19*(1+'3. Assumptions'!$B$37)
A20: Professional Services | B20: 20000 | E20: =B20 | F20: =E20*(1+'3. Assumptions'!$B$37) | G20: =F20*(1+'3. Assumptions'!$B$37) | H20: =G20*(1+'3. Assumptions'!$B$37) | I20: =H20*(1+'3. Assumptions'!$B$37)
A22: TOTAL OTHER OPEX | E22: =SUM(E17:E20) | F22: =SUM(F17:F20) | G22: =SUM(G17:G20) | H22: =SUM(H17:H20) | I22: =SUM(I17:I20)
A24: TOTAL OPERATING COSTS | E24: =E14+E22 | F24: =F14+F22 | G24: =G14+G22 | H24: =H14+H22 | I24: =I14+I22

Sheet Team - L
A1: TEAM COSTS — Zezamii LSC Model (Expanded)
A2: Current team + Sales/BD hires + Support hire (trigger-based)
A4: Role | B4: Person | C4: Full Cost | D4: Allocation | E4: Year 1 | F4: Year 2 | G4: Year 3 | H4: Year 4 | I4: Year 5
A5: Director | B5: Glenn | C5: 200000 | D5: 0.8 | E5: =C5*D5 | F5: =E5*(1+'3. Assumptions'!$B$36) | G5: =F5*(1+'3. Assumptions'!$B$36) | H5: =G5*(1+'3. Assumptions'!$B$36) | I5: =H5*(1+'3. Assumptions'!$B$36)
A6: Head of Engineering | B6: Kishan | C6: 170000 | D6: 1 | E6: =C6*D6 | F6: =E6*(1+'3. Assumptions'!$B$36) | G6: =F6*(1+'3. Assumptions'!$B$36) | H6: =G6*(1+'3. Assumptions'!$B$36) | I6: =H6*(1+'3. Assumptions'!$B$36)
A7: Fullstack Dev | B7: Duvan | C7: 110000 | D7: 1 | E7: =C7*D7 | F7: =E7*(1+'3. Assumptions'!$B$36) | G7: =F7*(1+'3. Assumptions'!$B$36) | H7: =G7*(1+'3. Assumptions'!$B$36) | I7: =H7*(1+'3. Assumptions'!$B$36)
A8: Co-founder | B8: Warren | C8: 200000 | D8: 0.5 | E8: =C8*D8 | F8: =E8*(1+'3. Assumptions'!$B$36) | G8: =F8*(1+'3. Assumptions'!$B$36) | H8: =G8*(1+'3. Assumptions'!$B$36) | I8: =H8*(1+'3. Assumptions'!$B$36)
A9: Support | B9: Luke | C9: 100000 | D9: 1 | E9: =C9*D9 | F9: =E9*(1+'3. Assumptions'!$B$36) | G9: =F9*(1+'3. Assumptions'!$B$36) | H9: =G9*(1+'3. Assumptions'!$B$36) | I9: =H9*(1+'3. Assumptions'!$B$36)
A11: TRIGGER-BASED HIRES
A12: Sales/BD #1 | B12: TBD | C12: 135000 | D12: 1 | E12: =IF(Revenue!C25>=200000, C12, 0) | F12: =IF(E12>0, E12*(1+'3. Assumptions'!$B$36), IF(Revenue!D25>=200000, C12, 0)) | G12: =IF(F12>0, F12*(1+'3. Assumptions'!$B$36), IF(Revenue!E25>=200000, C12, 0)) | H12: =IF(G12>0, G12*(1+'3. Assumptions'!$B$36), IF(Revenue!F25>=200000, C12, 0)) | I12: =IF(H12>0, H12*(1+'3. Assumptions'!$B$36), IF(Revenue!G25>=200000, C12, 0))
A13: Sales/BD #2 | B13: TBD | C13: 135000 | D13: 1 | E13: =IF(Revenue!C25>=500000, C13, 0) | F13: =IF(E13>0, E13*(1+'3. Assumptions'!$B$36), IF(Revenue!D25>=500000, C13, 0)) | G13: =IF(F13>0, F13*(1+'3. Assumptions'!$B$36), IF(Revenue!E25>=500000, C13, 0)) | H13: =IF(G13>0, G13*(1+'3. Assumptions'!$B$36), IF(Revenue!F25>=500000, C13, 0)) | I13: =IF(H13>0, H13*(1+'3. Assumptions'!$B$36), IF(Revenue!G25>=500000, C13, 0))
A14: Support #2 | B14: TBD | C14: 90000 | D14: 1 | E14: =IF(Revenue!C25>=500000, C14, 0) | F14: =IF(E14>0, E14*(1+'3. Assumptions'!$B$36), IF(Revenue!D25>=500000, C14, 0)) | G14: =IF(F14>0, F14*(1+'3. Assumptions'!$B$36), IF(Revenue!E25>=500000, C14, 0)) | H14: =IF(G14>0, G14*(1+'3. Assumptions'!$B$36), IF(Revenue!F25>=500000, C14, 0)) | I14: =IF(H14>0, H14*(1+'3. Assumptions'!$B$36), IF(Revenue!G25>=500000, C14, 0))
A15: Trigger: Sales/BD #1 @ $200K ARR | Sales/BD #2 + Support #2 @ $500K ARR
A17: TOTAL TEAM COST | E17: =SUM(E5:E9)+SUM(E12:E14) | F17: =SUM(F5:F9)+SUM(F12:F14) | G17: =SUM(G5:G9)+SUM(G12:G14) | H17: =SUM(H5:H9)+SUM(H12:H14) | I17: =SUM(I5:I9)+SUM(I12:I14)
A19: OTHER OPERATING COSTS
A20: Rent & Facilities | B20: 81250 | E20: =B20 | F20: =E20*(1+'3. Assumptions'!$B$37) | G20: =F20*(1+'3. Assumptions'!$B$37) | H20: =G20*(1+'3. Assumptions'!$B$37) | I20: =H20*(1+'3. Assumptions'!$B$37)
A21: Software & Subscriptions | B21: 62500 | E21: =B21 | F21: =E21*(1+'3. Assumptions'!$B$37) | G21: =F21*(1+'3. Assumptions'!$B$37) | H21: =G21*(1+'3. Assumptions'!$B$37) | I21: =H21*(1+'3. Assumptions'!$B$37)
A22: Insurance | B22: 18750 | E22: =B22 | F22: =E22*(1+'3. Assumptions'!$B$37) | G22: =F22*(1+'3. Assumptions'!$B$37) | H22: =G22*(1+'3. Assumptions'!$B$37) | I22: =H22*(1+'3. Assumptions'!$B$37)
A23: Professional Services | B23: 37500 | E23: =B23 | F23: =E23*(1+'3. Assumptions'!$B$37) | G23: =F23*(1+'3. Assumptions'!$B$37) | H23: =G23*(1+'3. Assumptions'!$B$37) | I23: =H23*(1+'3. Assumptions'!$B$37)
A25: TOTAL OTHER OPEX | E25: =SUM(E20:E23) | F25: =SUM(F20:F23) | G25: =SUM(G20:G23) | H25: =SUM(H20:H23) | I25: =SUM(I20:I23)
A27: TOTAL OPERATING COSTS | E27: =E17+E25 | F27: =F17+F25 | G27: =G17+G25 | H27: =H17+H25 | I27: =I17+I25

Sheet Team Summary
A1: TEAM COST SUMMARY — Selected Model
A3: Selected Team Model: | B3: ='2. Dashboard'!B7
A5: Cost Component | B5: Year 1 | C5: Year 2 | D5: Year 3 | E5: Year 4 | F5: Year 5
A6: Team Costs | B6: =IF($B$3="Product",'Team - S'!E9,IF($B$3="Zezamii",'Team - M'!E14,'Team - L'!E17)) | C6: =IF($B$3="Product",'Team - S'!F9,IF($B$3="Zezamii",'Team - M'!F14,'Team - L'!F17)) | D6: =IF($B$3="Product",'Team - S'!G9,IF($B$3="Zezamii",'Team - M'!G14,'Team - L'!G17)) | E6: =IF($B$3="Product",'Team - S'!H9,IF($B$3="Zezamii",'Team - M'!H14,'Team - L'!H17)) | F6: =IF($B$3="Product",'Team - S'!I9,IF($B$3="Zezamii",'Team - M'!I14,'Team - L'!I17))
A7: Other Opex | B7: =IF($B$3="Product",'Team - S'!E17,IF($B$3="Zezamii",'Team - M'!E22,'Team - L'!E25)) | C7: =IF($B$3="Product",'Team - S'!F17,IF($B$3="Zezamii",'Team - M'!F22,'Team - L'!F25)) | D7: =IF($B$3="Product",'Team - S'!G17,IF($B$3="Zezamii",'Team - M'!G22,'Team - L'!G25)) | E7: =IF($B$3="Product",'Team - S'!H17,IF($B$3="Zezamii",'Team - M'!H22,'Team - L'!H25)) | F7: =IF($B$3="Product",'Team - S'!I17,IF($B$3="Zezamii",'Team - M'!I22,'Team - L'!I25))
A9: TOTAL OPERATING COSTS | B9: =B6+B7 | C9: =C6+C7 | D9: =D6+D7 | E9: =E6+E7 | F9: =F6+F7
A11: COST SCALING
A12: Platform Revenue (SaaS) | B12: =Revenue!C80 | C12: =Revenue!D80 | D12: =Revenue!E80 | E12: =Revenue!F80 | F12: =Revenue!G80
A13: Min Opex % (from Assumptions) | B13: ='3. Assumptions'!B68 | C13: ='3. Assumptions'!B69 | D13: ='3. Assumptions'!B70 | E13: ='3. Assumptions'!B71 | F13: ='3. Assumptions'!B72
A14: Min Opex Required | B14: =B12*B13 | C14: =C12*C13 | D14: =D12*D13 | E14: =E12*E13 | F14: =F12*F13
A15: Base Opex (Team + Other) | B15: =B6+B7 | C15: =C6+C7 | D15: =D6+D7 | E15: =E6+E7 | F15: =F6+F7
A16: Additional Scaling Required | B16: =MAX(0,B14-B15) | C16: =MAX(0,C14-C15) | D16: =MAX(0,D14-D15) | E16: =MAX(0,E14-E15) | F16: =MAX(0,F14-F15)
A18: SCALED OPERATING COSTS
A19: Base Team Costs | B19: =B6 | C19: =C6 | D19: =D6 | E19: =E6 | F19: =F6
A20: Base Other Opex | B20: =B7 | C20: =C7 | D20: =D7 | E20: =E7 | F20: =F7
A21: Scaling Adjustment | B21: =B16 | C21: =C16 | D21: =D16 | E21: =E16 | F21: =F16
A22: TOTAL SCALED OPEX | B22: =B19+B20+B21 | C22: =C19+C20+C21 | D22: =D19+D20+D21 | E22: =E19+E20+E21 | F22: =F19+F20+F21
A23: Actual Opex % of Revenue | B23: =IF(B12>0,B22/B12,0) | C23: =IF(C12>0,C22/C12,0) | D23: =IF(D12>0,D22/D12,0) | E23: =IF(E12>0,E22/E12,0) | F23: =IF(F12>0,F22/F12,0)
